{"category_type":"topic","category_name":"audio-processing","repos_data":[{"full_name":"speechbrain/speechbrain","description":"A PyTorch-based Speech Toolkit","topics":["speech-recognition","speech-toolkit","speaker-recognition","speech-to-text","speech-enhancement","speech-separation","audio","audio-processing","speech-processing","speechrecognition"],"created_at":"2020-04-28T17:48:45Z","pushed_at":"2024-11-28T10:35:22Z","stargazers_count":8989,"language":"Python"},{"full_name":"bitgapp/eqMac","description":"macOS  System-wide Audio Equalizer & Volume Mixer  🎧","topics":["equalizer","osx","audio-effect","audio-applications","macos","audio-processing","swift","avaudioengine","audio","angular"],"created_at":"2017-07-23T12:04:10Z","pushed_at":"2024-11-28T01:03:02Z","stargazers_count":5751,"language":"Swift"},{"full_name":"pytorch/audio","description":"Data manipulation and transformation for audio signal processing, powered by PyTorch","topics":["audio","python","io","speech","machine-learning","pytorch","audio-processing"],"created_at":"2017-05-05T00:38:05Z","pushed_at":"2024-12-01T11:34:32Z","stargazers_count":2548,"language":"Python"},{"full_name":"vadymmarkov/Beethoven","description":":guitar: A maestro of pitch detection.","topics":["pitch-detection","audio","pitch-estimation","pitch-engine","audio-processing","swift","ios","tuner"],"created_at":"2015-10-27T23:02:13Z","pushed_at":"2021-09-06T20:36:59Z","stargazers_count":827,"language":"Ruby"},{"full_name":"Parisson/TimeSide","description":"scalable audio processing framework and server written in Python","topics":["audio-processing","python","web"],"created_at":"2011-11-21T21:48:08Z","pushed_at":"2024-10-14T17:26:35Z","stargazers_count":373,"language":"Shell"},{"full_name":"sahaRatul/sela","description":"SimplE Lossless Audio","topics":["lossless-compression-algorithm","audio-processing","codec"],"created_at":"2015-07-08T18:33:00Z","pushed_at":"2020-04-11T17:35:26Z","stargazers_count":210,"language":"C++"},{"full_name":"stingalleman/awesome-audiovisual","description":"Curated list of audiovisual projects","topics":["awesome","awesome-list","dmx","audiovisual","audio-processing","video-processing"],"created_at":"2020-04-15T08:34:59Z","pushed_at":"2024-07-01T10:13:28Z","stargazers_count":185,"language":"unknown"},{"full_name":"AmplitudeAudio/sdk","description":"A powerful cross-platform audio engine, optimized for games.","topics":["audio","audio-programming","sdk","cpp","game-development","game-engine","audio-processing","audio-filters","audio-effects","audio-engine"],"created_at":"2021-08-15T12:20:08Z","pushed_at":"2025-10-19T16:41:27Z","stargazers_count":60,"language":"CMake"},{"full_name":"dh1tw/gosamplerate","description":"Go Bindings for libsamplerate","topics":["golang","libsamplerate","audio","audio-processing","audio-library"],"created_at":"2016-11-20T21:19:31Z","pushed_at":"2024-01-28T01:50:34Z","stargazers_count":34,"language":"Go"}],"frecuent_topics":{"audio-processing":9,"audio":6,"swift":2,"python":2,"speech-recognition":1}}