{"category_type":"topic","category_name":"cocoapods","repos_data":[{"full_name":"SwiftyJSON/SwiftyJSON","description":"The better way to deal with JSON data in Swift.","topics":["swiftyjson","json","swift","response","request","carthage","cocoapods","json-parsing-library","json-parser","json-parsing-swift"],"created_at":"2014-06-18T14:41:15Z","pushed_at":"2024-11-14T11:02:39Z","stargazers_count":22691,"language":"Swift"},{"full_name":"SnapKit/SnapKit","description":"A Swift Autolayout DSL for iOS & OS X","topics":["auto","autolayout","snapkit","swift","xcode","dsl","cocoapods","constraints","layout","ui"],"created_at":"2014-06-05T21:13:40Z","pushed_at":"2024-07-07T13:58:39Z","stargazers_count":20001,"language":"Swift"},{"full_name":"SwifterSwift/SwifterSwift","description":"A handy collection of more than 500 native Swift extensions to boost your productivity.","topics":["swift","xcode","carthage","cocoapods","tvos","ios","macos","swifterswift","extensions","uikit"],"created_at":"2016-08-01T22:25:24Z","pushed_at":"2024-11-20T18:37:16Z","stargazers_count":14127,"language":"Swift"},{"full_name":"CocoaLumberjack/CocoaLumberjack","description":"A fast & simple, yet powerful & flexible logging framework for macOS, iOS, tvOS and watchOS","topics":["macos","ios","watchos","tvos","logging","log","objective-c","swift","cocoapods","carthage"],"created_at":"2011-03-31T02:38:39Z","pushed_at":"2024-11-19T18:37:10Z","stargazers_count":13216,"language":"Objective-C"},{"full_name":"SVProgressHUD/SVProgressHUD","description":"A clean and lightweight progress HUD for your iOS and tvOS app.","topics":["objective-c","hud","svprogresshud","carthage","progress","cocoapods","tvos","ios","apple","swift"],"created_at":"2011-03-28T19:23:04Z","pushed_at":"2024-08-08T13:49:17Z","stargazers_count":12440,"language":"Objective-C"},{"full_name":"xmartlabs/Eureka","description":"Elegant iOS form builder in Swift","topics":["ios","forms","ios-ui","swift","ios-forms","swift-library","carthage","cocoapods","uitableview","validations"],"created_at":"2015-09-28T22:20:53Z","pushed_at":"2024-09-12T17:04:03Z","stargazers_count":11786,"language":"Swift"},{"full_name":"ninjaprox/NVActivityIndicatorView","description":"A collection of awesome loading animations","topics":["swift","animation","ios","ios-ui","ios-animation","ios-swift","ios-thirdparty","ios-lib","carthage","cocoapods"],"created_at":"2015-07-21T15:01:17Z","pushed_at":"2024-04-17T15:35:05Z","stargazers_count":10641,"language":"Swift"},{"full_name":"WenchaoD/FSCalendar","description":"A fully customizable iOS calendar library, compatible with Objective-C and Swift","topics":["swift","objective-c","calendar","library","cocoapods","carthage","ios"],"created_at":"2015-02-15T08:43:09Z","pushed_at":"2024-08-10T13:44:15Z","stargazers_count":10609,"language":"Objective-C"},{"full_name":"Quick/Quick","description":"The Swift (and Objective-C) testing framework.","topics":["swift","cocoapods","objective-c","carthage","testing","bdd","ios"],"created_at":"2014-06-05T00:29:53Z","pushed_at":"2024-11-08T19:03:54Z","stargazers_count":9799,"language":"Objective-C"},{"full_name":"xmartlabs/XLPagerTabStrip","description":"Android PagerTabStrip for iOS.","topics":["pager-controller","ios-ui","ios-libraries","cocoapods","carthage","swift","swift-library"],"created_at":"2014-12-20T12:05:22Z","pushed_at":"2023-11-22T13:34:09Z","stargazers_count":6987,"language":"Objective-C"},{"full_name":"jverkoey/nimbus","description":"The iOS framework that grows only as fast as its documentation","topics":["objective-c","ios","ui","cocoapods"],"created_at":"2011-06-09T15:01:53Z","pushed_at":"2024-04-25T21:23:31Z","stargazers_count":6442,"language":"Objective-C"},{"full_name":"joeldev/JLRoutes","description":"URL routing library for iOS with a simple block-based API","topics":["routing","ios","ios-lib","objective-c","cocoapods","carthage","routing-engine","deeplink","deep-linking","deep-links"],"created_at":"2013-02-10T23:09:45Z","pushed_at":"2023-02-21T14:37:00Z","stargazers_count":5705,"language":"Ruby"},{"full_name":"jonkykong/SideMenu","description":"Simple side/slide menu control for iOS, no code necessary! Lots of customization. Add it to your project in 5 minutes or less.","topics":["sidemenu","cocoapods","carthage","storyboard","menus","xcode","swift","menu","slidemenu"],"created_at":"2015-12-25T07:57:01Z","pushed_at":"2023-02-09T09:07:10Z","stargazers_count":5693,"language":"Ruby"},{"full_name":"Yalantis/Koloda","description":"KolodaView is a class designed to simplify the implementation of Tinder like cards on iOS. ","topics":["ios","swift","kolodaview","animation","cocoapods","collectionview","koloda","cards","custom-layout","yalantis"],"created_at":"2015-07-02T16:32:08Z","pushed_at":"2024-05-29T20:58:30Z","stargazers_count":5379,"language":"Swift"},{"full_name":"KelvinJin/AnimatedCollectionViewLayout","description":"A UICollectionViewLayout subclass that adds custom transitions/animations to the UICollectionView without effecting your existing code.","topics":["swift","uicollectionview","uicollectionviewlayout-subclass","transition","animation","ios","cocoapods"],"created_at":"2017-02-08T06:57:03Z","pushed_at":"2020-09-20T07:09:55Z","stargazers_count":4750,"language":"Ruby"},{"full_name":"TimOliver/TOCropViewController","description":"A view controller for iOS that allows users to crop portions of UIImage objects","topics":["cropper","image","image-processing","ios","cocoapods","viewcontroller","crop-image","swift","podfile","crop"],"created_at":"2015-06-06T22:53:07Z","pushed_at":"2024-07-23T18:04:38Z","stargazers_count":4739,"language":"Ruby"},{"full_name":"ArtSabintsev/Siren","description":"Notify users when a new version of your app is available and prompt them to upgrade.","topics":["swift","alert","cocoapods","alerts","update","swift-package-manager","notify-users"],"created_at":"2015-01-03T23:28:11Z","pushed_at":"2024-05-05T00:30:00Z","stargazers_count":4265,"language":"Swift"},{"full_name":"Skyscanner/SkyFloatingLabelTextField","description":"A beautiful and flexible text field control implementation of  \"Float Label Pattern\". Written in Swift.","topics":["swift","interface-builder","cocoapods","textfield"],"created_at":"2015-12-21T08:40:49Z","pushed_at":"2024-05-27T06:12:35Z","stargazers_count":4102,"language":"Swift"},{"full_name":"JohnEstropia/CoreStore","description":"Unleashing the real power of Core Data with the elegance and safety of Swift","topics":["swift","coredata","core-data","swift-package-manager","cocoapods","carthage"],"created_at":"2014-12-14T12:26:04Z","pushed_at":"2024-10-31T07:37:58Z","stargazers_count":4012,"language":"Swift"},{"full_name":"ko1o/PYSearch","description":"🔍 An elegant search controller which replaces the UISearchController for iOS (iPhone & iPad) .","topics":["objective-c","search","swift","ios","ui","cocoapods","pod"],"created_at":"2016-10-23T07:11:26Z","pushed_at":"2020-09-30T01:35:57Z","stargazers_count":3827,"language":"Objective-C"},{"full_name":"Yalantis/FoldingTabBar.iOS","description":"Folding Tab Bar and Tab Bar Controller","topics":["ios","swift","animation","foldingtabbar","carthage","objective-c","protocol","cocoapods","tabbar","tabbarcontroller"],"created_at":"2015-04-03T09:14:41Z","pushed_at":"2022-06-13T14:56:56Z","stargazers_count":3678,"language":"Objective-C"},{"full_name":"xmartlabs/XLActionController","description":"Fully customizable and extensible action sheet controller written in Swift","topics":["ios","swift","cocoapods","carthage","ios-ui","uialertcontroller","swift-library"],"created_at":"2015-12-10T18:54:00Z","pushed_at":"2023-03-17T21:29:18Z","stargazers_count":3325,"language":"Swift"},{"full_name":"shoheiyokoyama/Gemini","description":"Gemini is rich scroll based animation framework for iOS, written in Swift.","topics":["swift","swift-library","ios","ios-animation","animation-effects","animation-library","uicollectionview","animation-3d","cocoapods","carthage"],"created_at":"2017-06-10T08:00:56Z","pushed_at":"2023-08-27T20:40:59Z","stargazers_count":3252,"language":"Swift"},{"full_name":"kaishin/Gifu","description":"High-performance animated GIF support for iOS in Swift","topics":["swift","carthage","gif","animation","cocoapods"],"created_at":"2014-09-07T21:46:51Z","pushed_at":"2025-08-17T07:20:07Z","stargazers_count":3183,"language":"Swift"},{"full_name":"dustturtle/RealReachability","description":"We need to observe the REAL reachability of network. That's what RealReachability do.","topics":["reachability","cocoapods","carthage","ping","scnetworkreachability-api","realreachability"],"created_at":"2016-01-21T07:38:01Z","pushed_at":"2022-10-12T01:28:08Z","stargazers_count":3093,"language":"Objective-C"},{"full_name":"mobileplayer/mobileplayer-ios","description":":iphone: :movie_camera: A powerful and completely customizable media player for iOS","topics":["mobile","video","video-player","player","ios","mobile-player","ads","cocoapods","swift"],"created_at":"2015-04-22T19:15:10Z","pushed_at":"2022-07-21T22:10:51Z","stargazers_count":3077,"language":"Swift"},{"full_name":"BeauNouvelle/FaceAware","description":"An extension that gives UIImageView the ability to focus on faces within an image.","topics":["swift","ios","uiimageview","extension","cocoapods","carthage","detect-faces","photos","face-detection","hacktoberfest"],"created_at":"2016-07-22T14:15:00Z","pushed_at":"2020-08-01T12:44:20Z","stargazers_count":3020,"language":"Swift"},{"full_name":"goktugyil/EZSwiftExtensions","description":":smirk: How Swift standard types and classes were supposed to work.","topics":["uikit","cocoapods","carthage","exswift","extension","swift","swift-extensions"],"created_at":"2015-11-14T16:10:25Z","pushed_at":"2024-04-05T13:43:05Z","stargazers_count":2999,"language":"Ruby"},{"full_name":"Yalantis/GuillotineMenu","description":"Our Guillotine Menu Transitioning Animation implemented in Swift reminds a bit of a notorious killing machine.","topics":["ios","swift","animation","protocol","cocoapods","guillotinemenu","transition-animation","yalantis"],"created_at":"2015-04-14T08:20:37Z","pushed_at":"2020-04-13T12:49:18Z","stargazers_count":2909,"language":"Swift"},{"full_name":"Yalantis/Side-Menu.iOS","description":"Animated side menu with customizable UI","topics":["ios","sidemenu","swift","cocoapods","menu","menubar","panel","navigation","animation","menu-navigation"],"created_at":"2015-01-19T08:45:06Z","pushed_at":"2020-04-13T06:45:38Z","stargazers_count":2717,"language":"Swift"},{"full_name":"pinterest/PINCache","description":"Fast, non-deadlocking parallel object cache for iOS, tvOS and OS X","topics":["carthage","cocoapods","objective-c","ios","cache"],"created_at":"2015-02-25T17:42:48Z","pushed_at":"2024-11-27T00:29:47Z","stargazers_count":2662,"language":"Ruby"},{"full_name":"3lvis/Sync","description":"JSON to Core Data and back. Swift Core Data Sync. ","topics":["coredata","json","swift","restkit","carthage","cocoapods","core-data","sync"],"created_at":"2014-11-02T09:24:29Z","pushed_at":"2024-06-10T22:55:43Z","stargazers_count":2555,"language":"Ruby"},{"full_name":"richardtop/CalendarKit","description":"📅 Calendar for Apple platforms in Swift","topics":["cocoapods","swift","ios","calendar","ios-ui","ios-calendar","ios-lib","ios-swift","calendarkit","swift-package-manager"],"created_at":"2015-10-19T13:45:05Z","pushed_at":"2024-11-03T17:34:29Z","stargazers_count":2543,"language":"Ruby"},{"full_name":"Yalantis/Segmentio","description":"Animated top/bottom segmented control written in Swift.","topics":["ios","swift","segmentio","carthage","cocoapods","animation","yalantis"],"created_at":"2016-07-04T08:54:51Z","pushed_at":"2024-08-12T05:33:14Z","stargazers_count":2529,"language":"Ruby"},{"full_name":"ytakzk/Fusuma","description":"Instagram-like photo browser and a camera feature with a few line of code in Swift.","topics":["swift","cocoapod","cocoapods","carthage","photo-browser","instagram","crop","ios","video"],"created_at":"2016-01-31T08:58:04Z","pushed_at":"2019-10-14T22:46:06Z","stargazers_count":2459,"language":"Swift"},{"full_name":"iziz/libPhoneNumber-iOS","description":"iOS port from libphonenumber (Google's phone number handling library)","topics":["libphonenumber","cocoapods","objective-c"],"created_at":"2014-02-26T09:09:15Z","pushed_at":"2024-08-25T15:34:39Z","stargazers_count":2361,"language":"Objective-C"},{"full_name":"Yalantis/DisplaySwitcher","description":"Custom transition between two collection view layouts","topics":["ios","yalantis","swift","custom-transitions","animation","cocoapods","transition-layout","custom-layout","display-switcher"],"created_at":"2016-04-11T09:27:42Z","pushed_at":"2021-07-15T14:13:46Z","stargazers_count":2326,"language":"Ruby"},{"full_name":"rhummelmose/BluetoothKit","description":"Easily communicate between iOS/OSX devices using BLE","topics":["bluetooth","bluetooth-low-energy","carthage","cocoapods","swift"],"created_at":"2015-08-26T14:02:56Z","pushed_at":"2023-10-06T13:26:35Z","stargazers_count":2278,"language":"Swift"},{"full_name":"gmarm/BetterSegmentedControl","description":"An easy to use, customizable replacement for UISegmentedControl & UISwitch.","topics":["swift","swift-3","ios","uiswitch","switch","uisegmentedcontrol","segmentedcontrol","carthage","cocoapods","ui"],"created_at":"2016-04-03T07:10:24Z","pushed_at":"2023-04-11T22:16:40Z","stargazers_count":2225,"language":"Ruby"},{"full_name":"muukii/NextGrowingTextView","description":"📝 The next in the generations of 'growing textviews' optimized for iOS 8 and above.","topics":["ios","carthage","xcode","textview","cocoapods","hacktoberfest"],"created_at":"2015-12-18T03:49:56Z","pushed_at":"2023-05-08T14:06:12Z","stargazers_count":1805,"language":"Swift"},{"full_name":"fdzsergio/SFFocusViewLayout","description":"UICollectionViewLayout with focused content","topics":["ios","swift","uicollectionviewlayout","carthage","cocoapods"],"created_at":"2015-10-07T11:22:14Z","pushed_at":"2018-09-29T16:30:27Z","stargazers_count":1761,"language":"Ruby"},{"full_name":"vhesener/Closures","description":"Swifty closures for UIKit and Foundation","topics":["swift","closures","convenience-methods","uicontrol","cocoapods","carthage","delegation","datasource","uigesturerecognizer","uiimagepickercontroller"],"created_at":"2017-07-16T04:38:53Z","pushed_at":"2021-04-29T15:34:36Z","stargazers_count":1744,"language":"Objective-C"},{"full_name":"Ekhoo/Device","description":"Light weight tool for detecting the current device and screen size written in swift.","topics":["carthage","xcode","cocoapods","swift","ios","swift-3","ipad","iphone","macos","osx"],"created_at":"2015-10-30T19:21:55Z","pushed_at":"2024-10-20T13:14:09Z","stargazers_count":1705,"language":"Swift"},{"full_name":"Brightify/Cuckoo","description":"Boilerplate-free mocking framework for Swift!","topics":["mock","mockito","cuckoo","stub","swift","matcher","protocol","mocking","unit-testing","cocoapods"],"created_at":"2016-01-12T14:30:36Z","pushed_at":"2024-11-20T21:46:57Z","stargazers_count":1672,"language":"Ruby"},{"full_name":"eddiekaiger/SwiftyAttributes","description":"A Swifty API for attributed strings","topics":["swift","cocoapods","swifty-api","nsattributedstring","macos","ios","watchos","tvos","cocoa","carthage"],"created_at":"2015-11-15T11:08:38Z","pushed_at":"2024-01-02T00:06:00Z","stargazers_count":1635,"language":"Swift"},{"full_name":"CaliCastle/PopMenu","description":"A fully customizable popup style menu for iOS 😎","topics":["swift","swift-library","ios","ios-swift","menu","actionsheet","cocoapods","carthage","popmenu","ios-library"],"created_at":"2018-04-12T23:35:22Z","pushed_at":"2024-03-12T06:52:56Z","stargazers_count":1630,"language":"Objective-C"},{"full_name":"jogendra/LoadingShimmer","description":"An easy way to add a shimmering effect to any view with just one line of code. It is useful as an unobtrusive loading indicator.","topics":["swift","swift4","ios11","cocoapods","animations","labels","xcode","library","framework","ios"],"created_at":"2018-04-06T11:48:30Z","pushed_at":"2022-10-22T13:31:11Z","stargazers_count":1592,"language":"Ruby"},{"full_name":"lovoo/NSFWDetector","description":"A NSFW (aka porn) detector with CoreML","topics":["coreml","swift","lovoo","ios","ios-library","cocoapods","machine-learning"],"created_at":"2018-08-14T09:21:41Z","pushed_at":"2024-08-29T13:35:18Z","stargazers_count":1590,"language":"Swift"},{"full_name":"thii/FontAwesome.swift","description":"Use FontAwesome in your Swift projects","topics":["swift","ios","font-awesome-5","macos","tvos","font-awesome","cocoapods","carthage"],"created_at":"2014-10-13T06:24:15Z","pushed_at":"2023-01-25T03:22:10Z","stargazers_count":1572,"language":"Swift"},{"full_name":"marcosgriselli/SwipeableTabBarController","description":"UITabBarController with swipe interaction between its tabs.","topics":["swift","ui","ios","xcode","tabbar","uitabbar","uitabbarcontroller","swipe","animation","cocoapods"],"created_at":"2017-02-01T20:04:06Z","pushed_at":"2023-06-04T21:52:42Z","stargazers_count":1545,"language":"Ruby"},{"full_name":"makomori/Sharaku","description":"（Not maintained）Image filtering UI library like Instagram.","topics":["ios","swift-3","swift","swift-library","instagram","cocoapods"],"created_at":"2017-01-04T00:02:53Z","pushed_at":"2021-01-18T18:53:28Z","stargazers_count":1513,"language":"Ruby"},{"full_name":"AladinWay/TransitionButton","description":"UIButton sublass for loading and transition animation.","topics":["button","transition","loading","animation","ios","swift","cocoapods","login","expand","shake"],"created_at":"2017-07-27T18:50:15Z","pushed_at":"2022-09-05T11:51:13Z","stargazers_count":1467,"language":"Ruby"},{"full_name":"nvzqz/RandomKit","description":"Random data generation in Swift","topics":["swift","random","random-generation","protocol","math","carthage","swift-package-manager","cocoapods","cross-platform","ios"],"created_at":"2015-10-10T22:35:12Z","pushed_at":"2022-06-09T18:49:03Z","stargazers_count":1464,"language":"Swift"},{"full_name":"yahoo/AppDevKit","description":"AppDevKit is an iOS development library that provides developers with useful features to fulfill their everyday iOS app development needs.","topics":["cocoapods","ios","app-development","objective-c","mobile"],"created_at":"2016-06-02T18:11:56Z","pushed_at":"2024-07-25T09:20:58Z","stargazers_count":1445,"language":"Ruby"},{"full_name":"TBXark/TKRubberIndicator","description":"A rubber animation pagecontrol","topics":["swift","cocoapods","carthage","page-control","coreanimation","ios","ios-animation","ui","uikit"],"created_at":"2015-10-28T02:14:22Z","pushed_at":"2024-08-21T09:11:19Z","stargazers_count":1440,"language":"Ruby"},{"full_name":"exyte/ConcentricOnboarding","description":"SwiftUI library for a walkthrough or onboarding flow with tap actions","topics":["ios","swiftui","onboarding","ui","cocoapods","swift","swift-library"],"created_at":"2019-09-09T08:21:56Z","pushed_at":"2024-07-10T06:29:11Z","stargazers_count":1421,"language":"Ruby"},{"full_name":"Yalantis/ColorMatchTabs","description":"This is a Review posting app that let user find interesting places near them","topics":["ios","swift","tabs","segmented-controls","animation","cocoapods","yalantis","carthage"],"created_at":"2016-07-28T11:51:41Z","pushed_at":"2020-04-09T10:41:50Z","stargazers_count":1380,"language":"Ruby"},{"full_name":"BenEmdon/CenteredCollectionView","description":"A lightweight UICollectionViewLayout that 'pages' and centers its cells 🎡 written in Swift","topics":["ios","carousel","uicollectionview","uicollectionviewflowlayout","uicollectionviewlayout","tvos","cocoapods","carthage","swift","center"],"created_at":"2016-09-03T00:42:11Z","pushed_at":"2021-01-20T08:28:57Z","stargazers_count":1377,"language":"Swift"},{"full_name":"imaginary-cloud/CameraManager","description":"Simple Swift class to provide all the configurations you need to create custom camera view in your app","topics":["swift","ios","camera","video-recording","image-captioning","cocoapods","swift-package-manager","carthage","custom-camera","qrcode-reader"],"created_at":"2014-10-10T17:28:06Z","pushed_at":"2024-07-19T13:58:45Z","stargazers_count":1375,"language":"Ruby"},{"full_name":"LeonardoCardoso/SwiftLinkPreview","description":"It makes a preview from an URL, grabbing all the information such as title, relevant texts and images.","topics":["swift","flow","watchos","tvos","macos","ios","carthage","cocoapods","swift-package-manager","crawler"],"created_at":"2016-06-09T12:32:25Z","pushed_at":"2023-08-31T02:55:44Z","stargazers_count":1374,"language":"Ruby"},{"full_name":"3lvis/Networking","description":"Swift HTTP Networking with stubbing and caching support","topics":["swift","mocking","nsurlsession","networking","alamofire","moya","stubbing","carthage","cocoapods"],"created_at":"2015-02-22T09:59:21Z","pushed_at":"2024-10-13T22:31:59Z","stargazers_count":1360,"language":"Swift"},{"full_name":"younatics/YNDropDownMenu","description":"✨ Awesome Dropdown menu for iOS with Swift 5.0","topics":["cocoapods","dropdownmenu","dropdown-menus","dropdown","swift","menu","menubar","carthage","ios","swift5"],"created_at":"2017-02-19T12:53:02Z","pushed_at":"2019-03-31T08:18:35Z","stargazers_count":1345,"language":"Ruby"},{"full_name":"ortuman/SwiftForms","description":"A small and lightweight library written in Swift that allows you to easily create forms.","topics":["swiftforms","swift","carthage","cocoapods","forms","dictionary","selector-controllers"],"created_at":"2014-10-11T11:38:02Z","pushed_at":"2021-02-23T09:15:25Z","stargazers_count":1329,"language":"Swift"},{"full_name":"kf99916/TimelineTableViewCell","description":"Simple timeline view implemented by UITableViewCell","topics":["swift","timeline","uitableviewcell","cocoapods"],"created_at":"2016-10-20T09:09:38Z","pushed_at":"2020-12-14T03:29:24Z","stargazers_count":1325,"language":"Swift"},{"full_name":"yysskk/SwipeMenuViewController","description":"Swipable tab and menu View and ViewController.","topics":["swift-library","ios","animation-library","swipe-menu","cocoapods","carthage","swift"],"created_at":"2017-06-30T08:57:31Z","pushed_at":"2023-09-13T14:56:09Z","stargazers_count":1287,"language":"Swift"},{"full_name":"whitesmith/WSTagsField","description":"An iOS text field that represents tags, hashtags, tokens in general.","topics":["ios","tags","uitextfield","ui-components","hashtags","hashtag","swift-package-manager","swift","cocoapods","carthage-installation"],"created_at":"2016-07-04T09:56:23Z","pushed_at":"2022-10-20T06:32:55Z","stargazers_count":1285,"language":"Swift"},{"full_name":"efremidze/Cluster","description":"Easy Map Annotation Clustering 📍","topics":["map","cluster","clustering","mapkit","ios","swift","annotations","apple","cocoapods","carthage"],"created_at":"2017-04-13T08:40:54Z","pushed_at":"2023-11-20T08:14:25Z","stargazers_count":1275,"language":"Ruby"},{"full_name":"juanpablofernandez/SwiftyOnboard","description":"A swifty iOS framework that allows developers to create beautiful onboarding experiences.","topics":["ios","swift","cocoapods","onboarding","onboard","swifty","swiftyonboard","custom-layout","framework"],"created_at":"2017-03-26T23:02:36Z","pushed_at":"2022-03-25T03:45:39Z","stargazers_count":1253,"language":"Ruby"},{"full_name":"adamcichy/SwiftySound","description":"SwiftySound is a simple library that lets you play sounds with a single line of code.","topics":["swift","sound","play-sounds","swifty-sound","loop","xcode","ios","macos","tvos","cocoapods"],"created_at":"2017-02-21T16:17:06Z","pushed_at":"2024-03-09T23:38:28Z","stargazers_count":1250,"language":"Swift"},{"full_name":"willpowell8/LocalizationKit_iOS","description":"Realtime Dynamic localization translation delivery system for iOS and Mac OSX in Swift. Create and update texts from localization.com without needing to recompile or redeploy. Cocapod for iOS devices (iPad, iPhone, iPod Touch and Mac)","topics":["localization","realtime","cocoapods","language","translation","localization-kit"],"created_at":"2016-11-08T23:31:39Z","pushed_at":"2019-10-31T13:27:54Z","stargazers_count":1226,"language":"Swift"},{"full_name":"AppliKeySolutions/PandoraPlayer","description":"🅿️ PandoraPlayer is a lightweight music player for iOS, based on AudioKit and completely written in Swift.","topics":["music-player","music","player","audio","ios","swift","cocoapods","animation","equalizer","audiokit"],"created_at":"2017-08-08T12:26:42Z","pushed_at":"2022-12-06T09:28:12Z","stargazers_count":1188,"language":"Ruby"},{"full_name":"SwiftKitz/Appz","description":"📱 Launch external apps, and deeplink, with ease using Swift!","topics":["swift-3","deep-linking","ios","watchos","cocoapods","carthage","uiapplication","url"],"created_at":"2015-11-11T06:57:48Z","pushed_at":"2021-09-16T16:34:28Z","stargazers_count":1175,"language":"Swift"},{"full_name":"0x73/SwiftIconFont","description":"Icons fonts for iOS (Font Awesome 5, Iconic, Ionicon, Octicon, Themify, MapIcon, MaterialIcon, Foundation 3, Elegant Icon, Captain Icon)","topics":["uitextfield","uilabel","uibutton","swift","cocoapods","icons","font","fonts","uibarbuttonitem"],"created_at":"2015-02-23T11:05:20Z","pushed_at":"2022-08-05T12:12:28Z","stargazers_count":1168,"language":"Swift"},{"full_name":"ArtSabintsev/FontBlaster","description":"Programmatically load custom fonts into your iOS, macOS and tvOS app.","topics":["custom-fonts","swift","carthage","cocoapods","plist","swift-package-manager","tvos"],"created_at":"2015-05-06T02:43:14Z","pushed_at":"2024-08-29T14:27:46Z","stargazers_count":1161,"language":"Swift"},{"full_name":"candostdagdeviren/CDAlertView","description":"Highly customizable alertview and alert/notification/success/error/alarm popup written in Swift","topics":["popup","alert","alert-messages","alertview","alerts","warning","popup-window","carthage","cocoapods","swift5"],"created_at":"2016-10-30T17:40:59Z","pushed_at":"2020-12-13T21:17:01Z","stargazers_count":1145,"language":"Ruby"},{"full_name":"Lickability/PinpointKit","description":"Send better feedback","topics":["feedback","cocoapods","carthage","ios","swift"],"created_at":"2016-01-10T19:14:36Z","pushed_at":"2022-02-14T21:20:49Z","stargazers_count":1133,"language":"Objective-C"},{"full_name":"cats-oss/Sica","description":":deer: Simple Interface Core Animation. Run type-safe animation sequencially or parallelly","topics":["swift","animation","ios","cocoapods","carthage","macos","tvos","swift-package-manager"],"created_at":"2018-06-25T07:55:06Z","pushed_at":"2021-11-30T21:46:54Z","stargazers_count":1056,"language":"Swift"},{"full_name":"scihant/CTPanoramaView","description":"A library that displays spherical or cylindrical panoramas with touch or motion based controls.","topics":["panorama","equirectangular-panorama","360-photo","spherical-panoramas","cylindrical-panoramas","carthage","cocoapods"],"created_at":"2017-02-20T05:20:00Z","pushed_at":"2024-08-09T11:17:04Z","stargazers_count":1037,"language":"Ruby"},{"full_name":"skywinder/GaugeKit","description":"Kit for building custom gauges + easy reproducible Apple's style ring gauges.","topics":["gaugekit","carthage","cocoapods","swift","ios-sdk","gauge-plugin","gauges","gauge","graphics"],"created_at":"2015-06-19T09:59:47Z","pushed_at":"2022-04-10T17:09:05Z","stargazers_count":1027,"language":"Swift"},{"full_name":"FabrizioBrancati/BFKit-Swift","description":"BFKit-Swift is a collection of useful classes, structs and extensions to develop Apps faster.","topics":["carthage","swift","swift-extensions","xcode","swift-package-manager","ios","linux","cocoapods","foundation","uikit"],"created_at":"2015-04-01T20:46:51Z","pushed_at":"2020-11-01T16:48:14Z","stargazers_count":1003,"language":"Swift"},{"full_name":"kaishin/ImageScout","description":"A Swift implementation of fastimage. Supports PNG, GIF, and JPEG.","topics":["carthage","swift","fastimage","cocoapods","image-processing","swiftpm"],"created_at":"2014-10-11T11:57:09Z","pushed_at":"2019-11-30T17:33:33Z","stargazers_count":974,"language":"Swift"},{"full_name":"ArtSabintsev/Zephyr","description":"Effortlessly synchronize UserDefaults over iCloud.","topics":["swift","nsuserdefaults","icloud","sync","nsubiquitouskeyvaluestore","icloud-sync","cocoapods","carthage","swift-package-manager","userdefaults"],"created_at":"2015-11-04T23:22:15Z","pushed_at":"2024-08-29T14:27:04Z","stargazers_count":940,"language":"Ruby"},{"full_name":"TBXark/TKSwitcherCollection","description":"An animation switch collection","topics":["swift","cocoapods","carthage","switcher","widget","ios","ios-animation","coreanimation","ui","uikit"],"created_at":"2015-10-26T08:19:54Z","pushed_at":"2024-08-21T09:13:19Z","stargazers_count":918,"language":"Swift"},{"full_name":"edopelawi/CascadingTableDelegate","description":"A no-nonsense way to write cleaner UITableViewDelegate and UITableViewDataSource in Swift.","topics":["uitableviewdelegate","uitableviewdatasource","uitableview","swift","ios","clean-code","carthage","cocoapods","rich-pages","ios-ui"],"created_at":"2016-10-19T07:29:13Z","pushed_at":"2019-10-15T05:36:13Z","stargazers_count":911,"language":"Ruby"},{"full_name":"fxm90/GradientLoadingBar","description":"⌛️A customizable animated gradient loading bar.","topics":["ios","swift","cocoapods","loading-animations","loading-bar","loading-indicator","gradient"],"created_at":"2016-12-27T20:26:45Z","pushed_at":"2024-09-06T19:01:08Z","stargazers_count":889,"language":"Ruby"},{"full_name":"ruddfawcett/Notepad","description":"[iOS] A fully themeable markdown editor with live syntax highlighting.","topics":["theme","regex","cocoapods","notepad","uitextview","syntax-highlighter","markdown","ios"],"created_at":"2016-10-15T04:30:07Z","pushed_at":"2021-11-14T10:26:25Z","stargazers_count":880,"language":"Swift"},{"full_name":"Yalantis/Preloader.Ophiuchus","description":"Custom Label to apply animations on whole text or letters.","topics":["ios","yalantis","coretext","custom-labels","cocoapods","objective-c","letters","sublayer","animation","mask"],"created_at":"2015-03-20T08:54:09Z","pushed_at":"2020-06-04T19:45:48Z","stargazers_count":880,"language":"Objective-C"},{"full_name":"vtourraine/VTAcknowledgementsViewController","description":"Acknowledgements screen displaying a list of licenses, for example from CocoaPods dependencies.","topics":["ios","objective-c","cocoapods","tvos","uikit"],"created_at":"2013-12-24T18:02:22Z","pushed_at":"2022-05-25T13:10:20Z","stargazers_count":857,"language":"Objective-C"},{"full_name":"LowKostKustomz/StatusAlert","description":"Display Apple system-like self-hiding status alerts. It is well suited for notifying user without interrupting user flow in iOS-like way.","topics":["carthage","cocoapods","swift","ios","alert","apple","swift-package-manager","system","private-api","private-framework"],"created_at":"2017-12-07T19:02:16Z","pushed_at":"2023-09-12T08:49:23Z","stargazers_count":846,"language":"Ruby"},{"full_name":"500px/greedo-layout-for-ios","description":"Full aspect ratio grid layout for iOS","topics":["cocoapods","greedo-layout","ios","library","layout","uicollectionview","objective-c"],"created_at":"2016-02-02T21:13:51Z","pushed_at":"2017-05-18T06:23:21Z","stargazers_count":824,"language":"Ruby"},{"full_name":"iTofu/LCActionSheet","description":"一款简约而不失强大的 ActionSheet，微博、微信和 QQ 都采用了极其类似的样式，完全支持 Swift。","topics":["objective-c","cocoapods","actionsheet","alert","no-issue","swift","masonry","wechat","qq","weibo"],"created_at":"2015-04-26T16:23:43Z","pushed_at":"2023-08-01T07:22:16Z","stargazers_count":822,"language":"Ruby"},{"full_name":"JanGorman/Agrume","description":"🍋 A lemony fresh iOS image viewer written in Swift.","topics":["swift","image","image-viewer","ios","cocoapods","carthage"],"created_at":"2015-05-23T16:20:29Z","pushed_at":"2024-10-29T07:56:31Z","stargazers_count":814,"language":"Swift"},{"full_name":"efremidze/Shiny","description":"Iridescent Effect View (inspired by Apple Pay Cash) ✨","topics":["ios","swift","cocoapods","carthage","animation","apple-pay","cash","shiny","hologram","holographic"],"created_at":"2017-12-09T03:14:14Z","pushed_at":"2023-11-20T08:16:51Z","stargazers_count":810,"language":"Swift"},{"full_name":"jogendra/BadgeHub","description":"A way to quickly add a notification badge icon to any view. Make any view of a full-fledged animated notification center.","topics":["swift","xcode","cocoapods","swift-framework","pod","podfile","notifications","swift-language","ios","animations"],"created_at":"2019-02-06T11:53:12Z","pushed_at":"2022-06-17T15:19:45Z","stargazers_count":810,"language":"Ruby"},{"full_name":"MaxDesiatov/XMLCoder","description":"Easy XML parsing using Codable protocols in Swift","topics":["xml","xml-parser","swift","swift4","codable","carthage","cocoapods","encoder","decoder","xml-serializer"],"created_at":"2018-11-08T09:26:06Z","pushed_at":"2024-02-12T11:28:37Z","stargazers_count":804,"language":"Swift"},{"full_name":"FabrizioBrancati/BFKit","description":"BFKit is a collection of useful classes and categories to develop Apps faster.","topics":["bfkit","objective-c","carthage","xcode","cocoapods","uikit","foundation","objective-c-extensions","ios"],"created_at":"2014-11-15T16:45:40Z","pushed_at":"2020-05-25T10:33:18Z","stargazers_count":797,"language":"Ruby"},{"full_name":"calimarkus/JDFlipNumberView","description":"[iOS] Animated analog flip numbers like airport/train-station displays (Swift/SwiftUI ready)","topics":["ios","animation","cocoapod","customizable","views","cocoapods","swiftui"],"created_at":"2012-03-25T20:02:27Z","pushed_at":"2022-07-02T04:33:01Z","stargazers_count":787,"language":"Objective-C"},{"full_name":"Draveness/NightNight","description":"Elegant way to integrate night mode to swift projects","topics":["night-mode","carthage","cocoapods","swift","theme","color"],"created_at":"2016-06-24T12:26:24Z","pushed_at":"2019-10-02T20:13:50Z","stargazers_count":774,"language":"Swift"},{"full_name":"efremidze/Haptica","description":"Easy Haptic Feedback Generator 📳","topics":["haptic","taptic","ios","swift","ios10","vibrate","feedback","uibutton","carthage","cocoapods"],"created_at":"2017-03-31T22:09:07Z","pushed_at":"2022-08-28T01:25:50Z","stargazers_count":774,"language":"Swift"},{"full_name":"sgr-ksmt/PDFGenerator","description":"A simple generator of PDF written in Swift. ","topics":["pdf","swift","carthage","cocoapods","generator","ios","swift-library","apple-swift","tool"],"created_at":"2016-02-04T13:00:50Z","pushed_at":"2020-10-27T14:30:02Z","stargazers_count":758,"language":"Swift"},{"full_name":"shoheiyokoyama/Koyomi","description":"Simple customizable calendar component in Swift :calendar:","topics":["swift","calendar","ios","swift3","carthage","cocoapods","customizable","ui","ui-components","uicollectionview"],"created_at":"2016-10-09T13:41:26Z","pushed_at":"2019-01-17T15:54:22Z","stargazers_count":749,"language":"Swift"},{"full_name":"Techprimate/TPPDF","description":"TPPDF is a simple-to-use PDF builder for iOS and macOS written in Swift","topics":["cocoapods","pdf","generator","builder","ios","swift"],"created_at":"2016-08-16T00:43:33Z","pushed_at":"2024-11-11T08:00:53Z","stargazers_count":747,"language":"Ruby"},{"full_name":"Vaberer/Font-Awesome-Swift","description":"Font Awesome swift library for iOS. ","topics":["swift","font-awesome","cocoapods","swift-3","swift-library","font-icons","font","ios","icons","xcode"],"created_at":"2015-07-14T12:34:20Z","pushed_at":"2020-07-20T22:30:08Z","stargazers_count":743,"language":"Swift"},{"full_name":"gkye/ComplimentaryGradientView","description":"Create complementary gradients generated from dominant and prominent colors in supplied image. Inspired by Grade.js","topics":["cocoapods","gradient","color","swift","ios"],"created_at":"2016-08-23T03:55:43Z","pushed_at":"2019-08-09T02:53:42Z","stargazers_count":729,"language":"Swift"},{"full_name":"troystribling/BlueCap","description":"iOS Bluetooth LE framework","topics":["bluetooth-low-energy","bluetooth-beacons","swift-framework","corebluetooth","peripherals","cocoapods","carthage","centralmanager","peripheralmanager","swift"],"created_at":"2014-06-04T02:18:50Z","pushed_at":"2023-02-10T17:28:42Z","stargazers_count":716,"language":"Swift"},{"full_name":"handsomecode/InteractiveSideMenu","description":"iOS Interactive Side Menu written in Swift.","topics":["swift","carthage","cocoapods","sidemenu","sidebar-menu"],"created_at":"2017-01-20T10:17:09Z","pushed_at":"2020-09-27T10:15:23Z","stargazers_count":708,"language":"Ruby"},{"full_name":"swiftyfinch/Rugby","description":"🏈 Cache CocoaPods for faster rebuild and indexing Xcode project.","topics":["cache-pods","cocoapods-optimisation","xcode-indexing","xcode-performance","cocoapods-performance","cocoapods-frameworks","cache-cocoapods","cocoapods-binary","cocoapods","xcode"],"created_at":"2021-02-13T10:23:57Z","pushed_at":"2024-11-28T07:23:34Z","stargazers_count":689,"language":"Swift"},{"full_name":"TBXark/PinterestSegment","description":"A Pinterest-like segment control with masking animation.","topics":["swift","cocoapods","pinterest","segment","widget","ios-animation","coreanimation"],"created_at":"2016-12-06T12:08:42Z","pushed_at":"2024-08-21T09:12:28Z","stargazers_count":688,"language":"Swift"},{"full_name":"WorldDownTown/ZoomTransitioning","description":"ZoomTransitioning provides a custom transition with image zooming animation and swiping the screen edge.","topics":["cocoapods","carthage","swift","ios","animation","custom-transitions"],"created_at":"2016-07-07T23:00:29Z","pushed_at":"2019-07-01T23:52:56Z","stargazers_count":672,"language":"Ruby"},{"full_name":"ArtSabintsev/Guitar","description":"A Cross-Platform String and Regular Expression Library written in Swift.","topics":["string-manipulation","swift","cross-platform","ios","tvos","watchos","macos","swift-server","cocoapods","carthage"],"created_at":"2016-12-21T05:13:47Z","pushed_at":"2024-06-20T02:03:44Z","stargazers_count":659,"language":"Swift"},{"full_name":"marty-suzuki/URLEmbeddedView","description":"URLEmbeddedView automatically caches the object that is confirmed the Open Graph Protocol.","topics":["ogp","embedded","url","thumbnail","swift","carthage","cocoapods","ios","tvos"],"created_at":"2016-03-06T03:45:39Z","pushed_at":"2020-01-11T05:30:03Z","stargazers_count":650,"language":"Ruby"},{"full_name":"Boilertalk/Web3.swift","description":"A pure swift Ethereum Web3 library","topics":["ethereum","swift","ethereum-dapp","cocoapods","carthage","swift-package-manager","ios","macos","tvos","watchos"],"created_at":"2017-12-30T20:05:39Z","pushed_at":"2024-08-14T12:07:17Z","stargazers_count":649,"language":"Swift"},{"full_name":"bow-swift/bow","description":"🏹 Bow is a cross-platform library for Typed Functional Programming in Swift","topics":["functional-programming","category-theory","functor","monad","swift-library","free-monad","tagless-final","mtl","cocoapods","carthage"],"created_at":"2018-03-07T15:01:09Z","pushed_at":"2022-10-09T21:51:49Z","stargazers_count":648,"language":"Swift"},{"full_name":"tikhop/TPInAppReceipt","description":"Reading and Validating In App Purchase Receipt Locally.","topics":["cocoapods","swift","in-app-receipt","ios","osx","macos","receipt","in-app-purchase","payment","purchase"],"created_at":"2016-09-30T02:40:24Z","pushed_at":"2024-10-24T18:33:21Z","stargazers_count":643,"language":"Ruby"},{"full_name":"SvenTiigi/STLocationRequest","description":"Request the Location Services via a 3D 360° flyover MKMapView 🗺","topics":["swift","3d-flyover","location-services","permissions","mapview","cocoapods","carthage"],"created_at":"2015-12-05T10:34:40Z","pushed_at":"2020-02-22T18:46:37Z","stargazers_count":638,"language":"Ruby"},{"full_name":"malkouz/ListPlaceholder","description":"ListPlaceholder is a swift library allows you to easily add facebook style animated loading placeholder to your tableviews or collection views.","topics":["swift","facebook","tableview","cocoapods","swift-library","placeholder","objective-c","custom","animation","customizable"],"created_at":"2017-09-18T12:36:46Z","pushed_at":"2024-07-08T08:46:15Z","stargazers_count":638,"language":"Swift"},{"full_name":"peterprokop/SwiftOverlays","description":"SwiftOverlays is a Swift GUI library for displaying various popups and notifications","topics":["notifications","swiftoverlays","cocoapods","swift","swift-gui-library","ios","ios-ui","swift4","carthage"],"created_at":"2014-10-16T09:28:44Z","pushed_at":"2018-09-19T13:58:29Z","stargazers_count":631,"language":"Swift"},{"full_name":"rolandleth/LTHPasscodeViewController","description":"iOS 7 style Passcode Lock","topics":["passcode","keychain","lockscreen","cocoapods"],"created_at":"2013-09-18T19:17:46Z","pushed_at":"2024-04-12T06:20:51Z","stargazers_count":615,"language":"Objective-C"},{"full_name":"rinov/YoutubeKit","description":"YoutubeKit is a video player that fully supports Youtube IFrame API and YoutubeDataAPI for easily create a Youtube app","topics":["youtube","swift","api-wrapper","video-player","cocoapods","carthage","iframe-api","swift-package-manager"],"created_at":"2017-09-24T15:26:14Z","pushed_at":"2024-04-13T10:44:38Z","stargazers_count":611,"language":"Ruby"},{"full_name":"yahoojapan/SwiftyXMLParser","description":"Simple XML Parser implemented in Swift","topics":["swift","ios","xml-parser","carthage","cocoapods"],"created_at":"2016-04-27T05:53:44Z","pushed_at":"2023-01-18T23:35:59Z","stargazers_count":584,"language":"Ruby"},{"full_name":"AnderGoig/SwiftInstagram","description":"Instagram API client written in Swift","topics":["ios","swift","swift-library","instagram","instagram-client","instagram-api","instagram-lib","xcode","cocoapods","carthage"],"created_at":"2017-09-30T20:10:18Z","pushed_at":"2018-10-14T16:40:09Z","stargazers_count":580,"language":"Swift"},{"full_name":"KarimEbrahemAbdelaziz/SwiftyMenu","description":"Simple and Elegant Drop down menu for iOS 🔥💥","topics":["ios","cocoapods","iosdevelopment","3rd-party","dropdown-menu","swift5","drop","storyboard"],"created_at":"2019-04-17T21:02:17Z","pushed_at":"2024-05-12T16:28:51Z","stargazers_count":579,"language":"Ruby"},{"full_name":"joncardasis/ChromaColorPicker","description":":art: An intuitive iOS color picker built in Swift.","topics":["cocoapods","swift","color-picker","ios-animation","customizable","carthage","color","color-palette","color-theme","swift5"],"created_at":"2016-07-21T19:35:31Z","pushed_at":"2024-02-13T01:38:27Z","stargazers_count":569,"language":"Swift"},{"full_name":"onurersel/anim","description":"Swift animation library for iOS, tvOS and macOS.","topics":["animation","macos","tvos","swift-animation","animation-library","ios","swift4","carthage","cocoapods"],"created_at":"2016-01-15T12:26:07Z","pushed_at":"2021-03-09T04:35:34Z","stargazers_count":569,"language":"Swift"},{"full_name":"marty-suzuki/SABlurImageView","description":"You can use blur effect and it's animation easily to call only two methods.","topics":["uiimage","blur","cocoapods","carthage","swift-package-manager","tvos","macos","ios"],"created_at":"2015-03-27T07:05:51Z","pushed_at":"2020-11-10T17:42:36Z","stargazers_count":556,"language":"Ruby"},{"full_name":"keygx/GradientCircularProgress","description":"Customizable progress indicator library in Swift","topics":["ui","carthage","cocoapods","swift","xcode","progress-circle","customizable","ios"],"created_at":"2015-06-20T14:58:25Z","pushed_at":"2021-08-26T12:08:20Z","stargazers_count":544,"language":"Swift"},{"full_name":"fxm90/GradientProgressBar","description":"📊 A customizable gradient progress bar (UIProgressView).","topics":["ios","swift","cocoapods","uiprogressview","gradient"],"created_at":"2017-03-04T09:17:35Z","pushed_at":"2024-09-06T19:10:33Z","stargazers_count":535,"language":"Swift"},{"full_name":"bannzai/Gedatsu","description":"Gedatsu provide readable format about AutoLayout error console log","topics":["swift","xcode","cocoapods","swiftpackagemanager"],"created_at":"2020-05-04T13:53:12Z","pushed_at":"2020-08-14T13:16:30Z","stargazers_count":533,"language":"Swift"},{"full_name":"kizitonwose/PodsUpdater","description":"A macOS app that helps you manage dependency releases in your Podfile.","topics":["cocoapods","podfile","dependencies","macos-app"],"created_at":"2018-01-29T16:39:30Z","pushed_at":"2019-03-17T10:57:51Z","stargazers_count":531,"language":"Swift"},{"full_name":"RahulKatariya/SwiftFrameworkTemplate","description":"A template for new Swift iOS / macOS / tvOS / watchOS Framework project ready with travis-ci, cocoapods, Carthage, SwiftPM and a Readme file ","topics":["cocoapods","carthage","swift","cookiecutter","macos","watchos","tvos","ios","swift-package-manager","framework"],"created_at":"2016-10-04T08:50:54Z","pushed_at":"2021-07-12T23:53:14Z","stargazers_count":526,"language":"Swift"},{"full_name":"ferranabello/Viperit","description":"Viper Framework for iOS using Swift","topics":["viper","cocoapods","carthage","swift","swift5","swift-5"],"created_at":"2016-11-10T20:06:02Z","pushed_at":"2021-09-15T10:38:29Z","stargazers_count":513,"language":"Swift"},{"full_name":"oleghnidets/TweeTextField","description":"Lightweight set of text fields with nice animation and functionality 🚀 ","topics":["swift","ios","uitextfield","textfield","ui","animation","cocoapods","interface-builder","carthage","swift-package-manager"],"created_at":"2017-12-21T15:44:20Z","pushed_at":"2022-05-26T14:23:11Z","stargazers_count":491,"language":"Swift"},{"full_name":"sgr-ksmt/PullToDismiss","description":"You can dismiss modal viewcontroller like Facebook Messenger by pulling scrollview or navigationbar in Swift.","topics":["carthage","cocoapods","swift","swift-extensions","swift-framework","swift-library","swift-language","apple-swift","ui","ios"],"created_at":"2016-11-14T06:13:05Z","pushed_at":"2020-03-25T04:09:41Z","stargazers_count":487,"language":"Swift"},{"full_name":"fulldecent/swift6-module-template","description":"An opinionated starting point for awesome, reusable Swift 6 modules","topics":["swift","cocoapods","ios","template","xcode","swift-package-manager"],"created_at":"2016-09-13T03:17:48Z","pushed_at":"2025-08-14T20:04:57Z","stargazers_count":481,"language":"Swift"},{"full_name":"mukeshthawani/FAQView","description":"An easy to use FAQ view for iOS written in Swift","topics":["ios","swift","cocoapods","ui-components","swift4","swift-3"],"created_at":"2016-12-01T03:59:46Z","pushed_at":"2022-05-07T09:40:17Z","stargazers_count":473,"language":"Swift"},{"full_name":"PiXeL16/IBLocalizable","description":"Localize your views directly in Interface Builder with IBLocalizable","topics":["interface-builder","localized","translate","ios","cocoapods","interfacebuilder","ui-components","ui"],"created_at":"2016-07-30T03:01:08Z","pushed_at":"2022-10-05T19:21:22Z","stargazers_count":459,"language":"Objective-C"},{"full_name":"jegumhon/URWeatherView","description":"Show the weather effects onto view written in Swift4.2","topics":["weather","swift","lottie","lightning","image-kernel","glsl-shaders","cocoapods","carthage","snow","rain"],"created_at":"2017-04-21T09:28:48Z","pushed_at":"2019-01-07T11:50:57Z","stargazers_count":448,"language":"Swift"},{"full_name":"T-Pham/UITextField-Navigation","description":"🏄‍♂️ UITextField-Navigation makes it easier to navigate between UITextFields and UITextViews","topics":["swift","cocoapods","uitextfield","ios","carthage","xcode","storyboard","interface-builder","keyboard","uitextfield-navigation"],"created_at":"2016-06-19T16:35:35Z","pushed_at":"2022-01-11T15:19:26Z","stargazers_count":445,"language":"Ruby"},{"full_name":"ytakzk/Hokusai","description":"A Swift library to provide a bouncy action sheet","topics":["hokusai","cocoapods","swift-library","carthage","ios","uiactionsheet","uialertviewcontroller","demo","ui","uikit"],"created_at":"2015-07-12T15:18:22Z","pushed_at":"2017-11-13T07:33:02Z","stargazers_count":430,"language":"Swift"},{"full_name":"touchlane/SlideController","description":"Swipe between pages with an interactive title navigation control. Configure horizontal or vertical chains for unlimited pages amount. ","topics":["swift","cocoapods","ios","library","uipageviewcontroller","uiscrollview","awesome"],"created_at":"2017-08-16T11:44:59Z","pushed_at":"2022-08-17T15:29:04Z","stargazers_count":424,"language":"Ruby"},{"full_name":"aFrogleap/SimpleImageViewer","description":"A snappy image viewer with zoom and interactive dismissal transition.","topics":["image","viewer","imageviewer","swift","ios","fullscreen","carthage","cocoapods","spm","afrogleap"],"created_at":"2017-05-30T11:12:17Z","pushed_at":"2022-02-16T06:22:46Z","stargazers_count":423,"language":"Swift"},{"full_name":"johnnywjy/JYRadarChart","description":"an iOS open source Radar Chart implementation","topics":["objective-c","xcode","ios","chart","cocoapods"],"created_at":"2013-10-31T15:27:31Z","pushed_at":"2018-08-20T21:18:43Z","stargazers_count":421,"language":"Objective-C"},{"full_name":"PierrePerrin/ShadowView","description":"An iOS Library that makes shadows management easy on UIView.","topics":["shadow","swift-image","shadowview","uiview","cocoapods","uikit","ios","blur","blurview","blurred-images"],"created_at":"2017-07-25T20:57:12Z","pushed_at":"2024-08-29T15:01:07Z","stargazers_count":413,"language":"Swift"},{"full_name":"hirohisa/PageController","description":"Infinite paging controller, scrolling through contents and title bar scrolls with a delay","topics":["pagecontroller","scrolling","cocoapods","carthage","delay","scrollview-component"],"created_at":"2015-07-05T15:51:03Z","pushed_at":"2022-06-13T15:14:34Z","stargazers_count":407,"language":"Swift"},{"full_name":"VeinGuo/VGPlayer","description":"📺  A simple iOS video player by Vein.","topics":["swift","player","avplayer","video-player","cocoapods","background-playback","custom-player","ios","ios-swift","open-source"],"created_at":"2017-06-12T16:42:03Z","pushed_at":"2019-08-17T07:08:37Z","stargazers_count":400,"language":"Ruby"},{"full_name":"dollarshaveclub/ImageButter","description":"Makes dealing with images buttery smooth.","topics":["ios","webp","webp-images","swift","cocoapods"],"created_at":"2015-09-04T19:55:47Z","pushed_at":"2020-06-26T18:10:33Z","stargazers_count":392,"language":"C"},{"full_name":"timoliver/TOPasscodeViewController","description":"A modal passcode input and validation view controller for iOS","topics":["ios","objective-c","uiviewcontroller","passcode","password","cocoapods"],"created_at":"2017-05-16T04:04:56Z","pushed_at":"2023-11-01T10:27:37Z","stargazers_count":387,"language":"Objective-C"},{"full_name":"Restofire/Restofire","description":"Restofire is a protocol oriented networking client for Alamofire","topics":["alamofire","swift","carthage","cocoapods","xcode","networking","restofire","moya","urlsession","protocol-oriented-programming"],"created_at":"2015-10-25T16:08:52Z","pushed_at":"2022-04-28T22:05:42Z","stargazers_count":379,"language":"Objective-C"},{"full_name":"rolandleth/LTHRadioButton","description":"A radio button with a pretty animation","topics":["radio-buttons","checkbox","swift","cocoapods","animation"],"created_at":"2016-10-21T15:21:32Z","pushed_at":"2024-04-12T06:03:13Z","stargazers_count":370,"language":"Swift"},{"full_name":"MobileFirstInc/MFCard","description":"Easily integrate Credit Card payments module in iOS App. Swift 4.0 ","topics":["card","credit-card","validation","animation","ios","swift","payment","mobilefirst","cocoapods"],"created_at":"2016-11-07T10:29:51Z","pushed_at":"2020-07-29T06:15:25Z","stargazers_count":365,"language":"Swift"},{"full_name":"aromajoin/material-showcase-ios","description":"✨ An elegant way to guide your beloved users in iOS apps - Material Showcase.","topics":["ios-showcase","material-design","material-showcase","feature-discovery","tutorial-show","tap-target-view","taptargetview","swift","objective-c","cocoapods"],"created_at":"2017-05-05T09:28:12Z","pushed_at":"2024-03-29T10:51:54Z","stargazers_count":363,"language":"Ruby"},{"full_name":"manuelescrig/MEVHorizontalContacts","description":"An iOS UICollectionViewLayout subclass to show a list of contacts with configurable expandable items.","topics":["objective-c","objective-c-library","ios","ios-animation","cocoapods"],"created_at":"2016-04-23T16:45:28Z","pushed_at":"2016-08-25T16:10:34Z","stargazers_count":357,"language":"Objective-C"},{"full_name":"jkandzi/Progress.swift","description":":hourglass: Add beautiful progress bars to your loops.","topics":["carthage","swift","cocoapods","progress-bar","command-line"],"created_at":"2015-12-26T11:16:57Z","pushed_at":"2024-01-16T07:57:33Z","stargazers_count":349,"language":"Swift"},{"full_name":"andrealufino/Luminous","description":"Luminous provides you a lot of information about the system and a lot of handy methods to quickly get useful data on the iOS platform.","topics":["swift","system","ios","cocoapods","device","device-detection","battery","battery-level","version","disk-space"],"created_at":"2016-10-23T21:10:23Z","pushed_at":"2022-04-20T14:02:23Z","stargazers_count":344,"language":"Swift"},{"full_name":"JanGorman/MapleBacon","description":"🍁🥓 Lightweight and fast Swift library for image downloading, caching and transformations","topics":["swift","image","image-download","caching","uiimageview","xcode","cocoapods","carthage","swift5","combine"],"created_at":"2014-12-17T10:52:04Z","pushed_at":"2024-11-01T08:13:22Z","stargazers_count":341,"language":"Swift"},{"full_name":"meismyles/SwiftWebVC","description":"A drop-in inline browser for your Swift iOS app.","topics":["swift","webview","browser","cocoapods","ios"],"created_at":"2015-07-05T00:09:06Z","pushed_at":"2021-07-05T08:21:03Z","stargazers_count":329,"language":"Swift"},{"full_name":"horitaku46/Serrata","description":"Slide image viewer library similar to Twitter and LINE.","topics":["swift4","swift-library","ios","images","image-viewer","carthage","cocoapods"],"created_at":"2017-12-14T06:01:57Z","pushed_at":"2018-09-27T05:10:29Z","stargazers_count":325,"language":"Swift"},{"full_name":"scottrhoyt/SwiftyTextTable","description":"A lightweight library for generating text tables.","topics":["swift","linux","command-line","tabular-data","macos","swift-package-manager","carthage","cocoapods"],"created_at":"2016-02-04T05:42:16Z","pushed_at":"2023-02-25T21:18:37Z","stargazers_count":319,"language":"Objective-C"},{"full_name":"marty-suzuki/MisterFusion","description":"MisterFusion is Swift DSL for AutoLayout. It is the extremely clear, but concise syntax, in addition, can be used in both Swift and Objective-C. Support Safe Area and Size Class.","topics":["autolayout","swift","ios","iphone-x","safe-area","carthage","cocoapods","tvos","macos"],"created_at":"2015-11-13T07:06:54Z","pushed_at":"2019-09-30T16:55:35Z","stargazers_count":314,"language":"Ruby"},{"full_name":"keitaoouchi/IoniconsKit","description":"Use Ionicons in your Swift projects.","topics":["ios-ui","carthage","cocoapods","ios-swift","uifont","uiimage","swift","ionicons"],"created_at":"2016-09-17T06:07:05Z","pushed_at":"2022-07-22T00:58:14Z","stargazers_count":312,"language":"Swift"},{"full_name":"PiXeL16/PasswordTextField","description":"A custom TextField with a switchable icon which shows or hides the password and enforce good password policies","topics":["passwordtextfield","password","textfield","carthage","cocoapods","swift","custom-textfield"],"created_at":"2016-02-10T05:50:12Z","pushed_at":"2024-06-01T09:51:53Z","stargazers_count":310,"language":"Objective-C"},{"full_name":"yervandsar/ExpandedTabBar","description":"ExpandedTabBar is a very creative designed solution for \"more\" items in UITabBarController. It's greate experience to have more comfortable and intuitive UI.","topics":["uitabbarcontroller","ios","swift","tabbar","tabbarcontroller","customui","swiftpackagemanager","cocoapods"],"created_at":"2018-03-14T08:57:53Z","pushed_at":"2023-01-12T18:22:58Z","stargazers_count":309,"language":"Ruby"},{"full_name":"wwt/SwiftCurrent","description":"A library for managing complex workflows in Swift","topics":["swift","ios","uikit","workflows","workflow","swift-package-manager","cocoapods","swiftui","watchos","tvos"],"created_at":"2019-09-01T04:43:10Z","pushed_at":"2023-01-29T02:35:16Z","stargazers_count":307,"language":"Ruby"},{"full_name":"SURYAKANTSHARMA/CountryPicker","description":"A simple, customizable Country picker for picking country or dialing code. 🇮🇳 🇯🇵 🇰🇷 🇩🇪 🇨🇳 🇺🇸 🇫🇷 🇪🇸 🇮🇹 🇷🇺 🇬🇧 ","topics":["ios","country-picker","cocoapods","xcode","country-flags","countrylist","countrycodes","country-selection","swift","filter-countries"],"created_at":"2017-10-28T12:31:36Z","pushed_at":"2024-10-30T06:43:40Z","stargazers_count":298,"language":"Swift"},{"full_name":"manuelescrig/MEVFloatingButton","description":"An iOS drop-in UITableView, UICollectionView and UIScrollView superclass category for showing a customizable floating button on top of it.","topics":["objective-c","objective-c-library","objective-c-extensions","ios","ios-animation","cocoapods"],"created_at":"2016-01-27T09:37:27Z","pushed_at":"2017-03-22T15:30:04Z","stargazers_count":296,"language":"Objective-C"},{"full_name":"chriszielinski/Ribbon","description":"🎀 A simple cross-platform toolbar/custom input accessory view library for iOS & macOS.","topics":["macos","ios","carthage","cocoapods","ribbon","toolbar","custom-input-accessory-view","dark-mode","swift","cross-platform"],"created_at":"2019-08-07T19:43:10Z","pushed_at":"2021-09-10T05:54:49Z","stargazers_count":295,"language":"Makefile"},{"full_name":"andresilvagomez/Localize","description":"Localize is a framework writed in swift to localize your projects easier improves i18n, including storyboards and strings.","topics":["swift","localization","localized","xcode","cocoapods","json","carthage","storyboards","language","storyboard"],"created_at":"2017-01-13T23:20:34Z","pushed_at":"2021-09-17T08:12:38Z","stargazers_count":293,"language":"Swift"},{"full_name":"hirohisa/ImageLoaderSwift","description":"A lightweight and fast image loader for iOS written in Swift.","topics":["imageloader","swift","carthage","uiimageview","cocoapods","xcode"],"created_at":"2014-10-23T12:26:58Z","pushed_at":"2019-05-18T07:35:48Z","stargazers_count":292,"language":"Objective-C"},{"full_name":"jinSasaki/Vulcan","description":"Multi image downloader with priority in Swift","topics":["swift","swift-3","cocoapods","carthage","image","webp"],"created_at":"2016-10-20T14:52:23Z","pushed_at":"2017-09-25T06:01:12Z","stargazers_count":292,"language":"Swift"},{"full_name":"Mijick/Camera","description":"Camera made simple. The ultimate camera library that significantly reduces implementation time and effort. Written with and for SwiftUI.","topics":["cocoapods","ios","ios-sdk","ios-swift","mobile","swift","swift-5","swift-library","swift-package","swift-package-manager"],"created_at":"2024-04-01T22:48:29Z","pushed_at":"2024-12-16T10:44:43Z","stargazers_count":292,"language":"Swift"},{"full_name":"LeonardoCardoso/AudioIndicatorBars","description":"AIB indicates for your app users which audio is playing. Just like the Podcasts app.","topics":["tvos","ios","audio","xcode","carthage","cocoapods","swift"],"created_at":"2016-09-16T12:48:40Z","pushed_at":"2018-06-25T11:04:15Z","stargazers_count":289,"language":"Ruby"},{"full_name":"tungvoduc/DTPagerController","description":"A fully customizable container view controller to display a set of ViewControllers in a horizontal scroll view. Written in Swift.","topics":["swift","swift4","pager-controller","xcode","ios","cocoapods","swift5","swift-package-manager"],"created_at":"2017-09-15T21:38:09Z","pushed_at":"2021-04-11T14:09:04Z","stargazers_count":289,"language":"Ruby"},{"full_name":"nodes-ios/Serpent","description":"A protocol to serialize Swift structs and classes for encoding and decoding.","topics":["swift","parsing","mapper","json","alamofire","decoding","cocoapods","model-boiler","encoding","carthage"],"created_at":"2016-02-09T15:10:04Z","pushed_at":"2022-03-10T09:17:42Z","stargazers_count":286,"language":"Swift"},{"full_name":"sgr-ksmt/Alertift","description":"Swifty, modern UIAlertController wrapper.","topics":["swift","alert","actionsheet","uikit","wrapper","library","cocoapods","carthage","modern"],"created_at":"2017-04-26T05:14:13Z","pushed_at":"2020-11-01T15:49:13Z","stargazers_count":283,"language":"Ruby"},{"full_name":"Swiftify-Corp/IHProgressHUD","description":"A clean and lightweight progress HUD based on SVProgressHUD, converted to Swift with the help of Swiftify.","topics":["swift4","svprogresshud","cocoapods","hud","activity-indicator","progress-circle","ios","tvos"],"created_at":"2018-11-22T16:04:59Z","pushed_at":"2023-10-08T03:34:15Z","stargazers_count":281,"language":"Swift"},{"full_name":"dogo/AKSideMenu","description":"Beautiful iOS side menu library with parallax effect. Written in Swift","topics":["cocoapods","sidemenu","parallax","carthage","swift","aksidemenu","ios","spm","swift-package-manager"],"created_at":"2016-06-09T13:46:42Z","pushed_at":"2024-10-28T19:14:11Z","stargazers_count":281,"language":"Ruby"},{"full_name":"tungvoduc/DTPhotoViewerController","description":"A fully customizable photo viewer ViewController to display single photo or collection of photos, inspired by Facebook photo viewer.","topics":["swift4","swift","photoviewer","cocoapod","cocoapods","xcode","swift5","swift-package-manager"],"created_at":"2016-05-06T23:29:39Z","pushed_at":"2021-10-24T13:24:06Z","stargazers_count":280,"language":"Ruby"},{"full_name":"isair/ManualLayout","description":"✂  Easy to use and flexible library for manually laying out views and layers for iOS and tvOS. Supports AsyncDisplayKit.","topics":["cocoapods","swift","layout","layout-engine","uiviewcontroller-properties","edges","position"],"created_at":"2015-02-23T19:59:23Z","pushed_at":"2020-04-23T14:57:56Z","stargazers_count":279,"language":"Swift"},{"full_name":"bow-swift/nef","description":"💊 steroids for Xcode Playgrounds","topics":["swift","playground","carbon","jekyll","functional-programming","apple-documentation","bow","cocoapods","nef","hacktoberfest"],"created_at":"2018-12-19T15:59:26Z","pushed_at":"2022-01-19T18:14:26Z","stargazers_count":267,"language":"Shell"},{"full_name":"Antondomashnev/ADChromePullToRefresh","description":"ADChromePullToRefresh","topics":["refresh-actions","pull-to-refresh","cocoapods"],"created_at":"2015-05-10T16:31:34Z","pushed_at":"2018-11-17T00:01:58Z","stargazers_count":266,"language":"Swift"},{"full_name":"SwiftKitz/Datez","description":"📆 Breeze through Date, DateComponents, and TimeInterval with Swift!","topics":["date","datetime","calendar","swift","timeinterval","ios","macos","watchos","tvos","cocoapods"],"created_at":"2015-11-07T17:52:39Z","pushed_at":"2020-12-04T08:18:18Z","stargazers_count":261,"language":"Swift"},{"full_name":"vinnyoodles/mosaic-layout","description":"A mosaic collection view layout inspired by Lightbox's Algorithm, written in Swift 🔶","topics":["swift","cocoapods","lightbox-algorithm"],"created_at":"2016-07-03T14:16:17Z","pushed_at":"2019-11-08T12:12:17Z","stargazers_count":250,"language":"Ruby"},{"full_name":"gkaimakas/SwiftValidators","description":"String (and more) validation for iOS","topics":["validation","validators","ios","swift","swift-3","swift3","swift-package-manager","cocoapods","app","application"],"created_at":"2015-07-22T16:44:49Z","pushed_at":"2022-01-12T13:54:30Z","stargazers_count":240,"language":"Swift"},{"full_name":"robertherdzik/RHPlaceholder","description":"Show pleasant loading view for your users 😍","topics":["swift","animation","ios","ios-ui","ios-uiview","ios-animation","ios-swift","ios-lib","cocoapods","loading-animations"],"created_at":"2018-02-06T22:36:10Z","pushed_at":"2021-11-21T16:09:34Z","stargazers_count":238,"language":"Swift"},{"full_name":"dingwilson/MultiPeer","description":"📱📲 A wrapper for the MultipeerConnectivity framework for automatic offline data transmission between devices","topics":["ios","swift","multipeerconnectivity","connection","mesh-networks","cocoapods","multipeer","carthage","multipeerconnectivity-framework","swift-package-manager"],"created_at":"2018-02-02T04:47:19Z","pushed_at":"2021-05-28T04:17:17Z","stargazers_count":226,"language":"Ruby"},{"full_name":"marty-suzuki/TheAnimation","description":"Type-safe CAAnimation wrapper. It makes preventing to set wrong type values.","topics":["carthage","animation","cocoapods","ios","macos","tvos"],"created_at":"2018-05-12T05:17:25Z","pushed_at":"2020-01-20T18:44:40Z","stargazers_count":223,"language":"Ruby"},{"full_name":"4taras4/CountryCode","description":" 🎯 Swift country and phone code Picker","topics":["picker","countrypicker","swift","phonecode","uipickerview","phonepicker","flags","countries","cocoapods","ios"],"created_at":"2016-12-02T15:57:24Z","pushed_at":"2024-04-24T09:35:00Z","stargazers_count":216,"language":"Ruby"},{"full_name":"kubatruhlar/AFNetworking-RetryPolicy","description":"Nice category that adds the ability to set the retry interval, retry count and progressiveness.","topics":["afnetworking","objective-c","cocoapods","ios","retry-policy"],"created_at":"2016-08-26T23:04:21Z","pushed_at":"2022-08-17T22:26:41Z","stargazers_count":212,"language":"Objective-C"},{"full_name":"TBXark/TKRadarChart","description":"A customizable radar chart  in Swift","topics":["swift","cocoapods","carthage","radar-chart","chart"],"created_at":"2016-07-13T09:05:29Z","pushed_at":"2023-04-11T05:40:36Z","stargazers_count":210,"language":"Swift"},{"full_name":"rchatham/SwiftyAnimate","description":"Composable animations in Swift","topics":["swift-3","animation","ios","swift","cocoapods","carthage","composable-animations","animations","tested"],"created_at":"2016-10-19T03:29:07Z","pushed_at":"2017-10-02T01:59:49Z","stargazers_count":194,"language":"Swift"},{"full_name":"touchlane/CampcotCollectionView","description":"Collapse and expand UICollectionView sections with one method call.","topics":["swift","cocoapods","ios","library","awesome","uicollectionview","expandable","collapsible"],"created_at":"2018-01-25T13:59:37Z","pushed_at":"2022-06-15T16:02:20Z","stargazers_count":186,"language":"Swift"},{"full_name":"behrad-kzm/BEKCurveTabbar","description":"Full Customizable Tabbar with IBInspectables","topics":["uitabbar","uitabbarcontroller","ui-components","tabbar","swift","component","pod","cocoapods"],"created_at":"2019-12-21T13:27:21Z","pushed_at":"2020-05-23T06:04:05Z","stargazers_count":183,"language":"Objective-C"},{"full_name":"abdullahselek/Swifty360Player","description":"iOS 360-degree video player streaming from an AVPlayer.","topics":["360-video","uiview","uiviewcontroller","scenekit","avplayer","cocoapods","carthage","media","video","streaming"],"created_at":"2017-10-12T07:49:21Z","pushed_at":"2024-05-14T10:39:16Z","stargazers_count":179,"language":"Objective-C"},{"full_name":"marty-suzuki/DuctTape","description":"📦 KeyPath dynamicMemberLookup based syntax sugar for Swift.","topics":["swift","syntax-sugar","cocoapods","carthage","keypath-dynamicmemberlookup","swift-package-manager","ios","macos","tvos","watchos"],"created_at":"2019-10-01T18:31:52Z","pushed_at":"2021-06-03T01:49:06Z","stargazers_count":177,"language":"Swift"},{"full_name":"novalagung/nvdate","description":"📅 Swift4 Date extension library","topics":["swift","swift4","objective-c","cocoapods","ios"],"created_at":"2014-02-05T01:52:54Z","pushed_at":"2018-05-25T07:22:46Z","stargazers_count":174,"language":"Ruby"},{"full_name":"TimOliver/TOActionSheet","description":"A custom-designed reimplementation of the UIActionSheet control for iOS","topics":["ios","cocoapods","actionsheet","objective-c"],"created_at":"2015-09-11T15:01:06Z","pushed_at":"2021-09-09T02:21:14Z","stargazers_count":173,"language":"Objective-C"},{"full_name":"mukeshthawani/TriLabelView","description":"A triangle shaped corner label view for iOS written in Swift.","topics":["swift","cocoapods","ios","ui-components"],"created_at":"2016-07-10T14:21:29Z","pushed_at":"2024-08-07T14:27:38Z","stargazers_count":170,"language":"Objective-C"},{"full_name":"v-braun/VBPiledView","description":"Simple and beautiful stacked UIView to use as a replacement for an UITableView, UIImageView or as a menu","topics":["collectionview","uitableview","uicollectionview","uiimageview","cocoapods","ios","swift","imagegallery"],"created_at":"2016-07-02T20:07:17Z","pushed_at":"2018-12-25T12:20:28Z","stargazers_count":169,"language":"Swift"},{"full_name":"e-sites/Bluetonium","description":"Bluetooth mapping in Swift","topics":["ios","swift","bluetooth-low-energy","bluetooth","cocoapods","carthage","peripherals"],"created_at":"2016-01-11T07:55:30Z","pushed_at":"2019-08-13T05:23:11Z","stargazers_count":165,"language":"Ruby"},{"full_name":"TimOliver/TORoundedTableView","description":"A subclass of UITableView that styles it like Settings.app on iPad","topics":["uitableview","rounded-corners","cocoapods","ios"],"created_at":"2016-11-30T07:55:42Z","pushed_at":"2020-04-13T04:57:26Z","stargazers_count":160,"language":"Objective-C"},{"full_name":"sxg/ForecastIO","description":"A Swift library for the Forecast.io Dark Sky API","topics":["weather","swift","carthage","cocoapods","forecastio","darksky","cocoadocs"],"created_at":"2015-07-18T16:52:28Z","pushed_at":"2019-09-20T00:31:52Z","stargazers_count":159,"language":"Swift"},{"full_name":"sagaya/Wobbly","description":"(Animate CSS) animations for iOS. An easy to use library of iOS animations. As easy to use as an easy thing.","topics":["ios","iosanimation","swift","animatecss","swift4","swift-library","ios-swift","ios-animation","ios-ui","cocoapods"],"created_at":"2019-03-06T08:08:11Z","pushed_at":"2019-03-18T07:11:10Z","stargazers_count":152,"language":"Ruby"},{"full_name":"hryk224/PCLBlurEffectAlert","description":"Swift AlertController with UIVisualeffectview","topics":["uialertcontroller","cocoapods","swift","swift-alertcontroller","uivisualeffectview"],"created_at":"2015-10-12T12:03:48Z","pushed_at":"2018-08-09T20:03:20Z","stargazers_count":147,"language":"Swift"},{"full_name":"T-Pham/Switch","description":"💊 An iOS switch control implemented in Swift with full Interface Builder support","topics":["ios","swift","interface-builder","cocoapods","cartfile","podfile","carthage","uiswitch","storyboard"],"created_at":"2016-08-29T07:25:21Z","pushed_at":"2021-07-09T22:39:09Z","stargazers_count":145,"language":"Swift"},{"full_name":"fxm90/LightweightObservable","description":"📬 A lightweight implementation of an observable sequence that you can subscribe to.","topics":["swift","ios","mvvm","reactive-programming","rx","observer","observable","cocoapods"],"created_at":"2019-04-28T06:37:06Z","pushed_at":"2022-09-18T11:09:10Z","stargazers_count":135,"language":"Swift"},{"full_name":"gsabran/DDDKit","description":"360 video player for iOS written in swift - a subset of SceneKit that works","topics":["360-video","ios","cocoapods","3d-rendering","swift","scenekit"],"created_at":"2016-10-03T02:28:45Z","pushed_at":"2019-01-10T11:23:30Z","stargazers_count":133,"language":"Ruby"},{"full_name":"roycms/RCalendarPicker","description":"RCalendarPicker A date picker control, Calendar calendar control, select control, calendar, date selection, the clock selection control. 日历控件 ，日历选择控件，日历，日期选择，时钟选择控件","topics":["calendar","clock","cocoapods","calendar-display"],"created_at":"2016-11-16T06:53:33Z","pushed_at":"2017-03-01T07:05:20Z","stargazers_count":133,"language":"Ruby"},{"full_name":"JKalash/Croc","description":"Swift emoji string parsing library","topics":["ios","emoji","string","swift","cocoapods","xcode","carthage","embedded-framework","croc"],"created_at":"2018-02-14T17:27:39Z","pushed_at":"2019-01-10T13:07:59Z","stargazers_count":129,"language":"Ruby"},{"full_name":"Antondomashnev/ADPuzzleAnimation","description":"Inspired by Fabric - Answers animation. Allows to \"build\" given view with pieces. Allows to \"destroy\" given view into pieces","topics":["animation","puzzle","carthage","answers-animation","cocoapods"],"created_at":"2016-02-06T12:24:31Z","pushed_at":"2016-06-19T09:36:17Z","stargazers_count":125,"language":"Ruby"},{"full_name":"takasek/ActionClosurable","description":"Extensions which helps to convert objc-style target/action to  swifty closures","topics":["carthage","cocoapods","swift","ios","nsobject","target-action","selector","closure"],"created_at":"2016-04-16T09:27:47Z","pushed_at":"2019-08-13T13:47:15Z","stargazers_count":124,"language":"Swift"},{"full_name":"szweier/SZMentionsSwift","description":"Library to help handle mentions","topics":["mentions","textview","cocoapods","carthage"],"created_at":"2016-01-13T03:42:13Z","pushed_at":"2021-04-19T09:12:17Z","stargazers_count":121,"language":"Swift"},{"full_name":"benzamin/BBLocationManager","description":"A Location Manager for easily implementing location services & geofencing in iOS. Ready for iOS 11.","topics":["cocoapods","geocoder","location","corelocation","geofence","geofences","locationmanager","block","delegate","ios"],"created_at":"2017-01-29T10:03:12Z","pushed_at":"2018-01-18T11:14:55Z","stargazers_count":106,"language":"Objective-C"},{"full_name":"andreadelfante/PredicateFlow","description":"Write amazing, strong-typed and easy-to-read NSPredicate.","topics":["cocoapods","flow","autogenerated","code-generation","swift","ios","macos","watchos","tvos","realmswift"],"created_at":"2018-02-26T21:40:31Z","pushed_at":"2023-03-17T05:48:13Z","stargazers_count":101,"language":"Ruby"},{"full_name":"billp/TermiNetwork","description":"🌏 A zero-dependency networking solution for building modern and secure iOS, watchOS, macOS and tvOS applications.","topics":["networking","library","cocoapods","swift","swiftui","xcode","apple","carthage","swift-packages","deserialization"],"created_at":"2018-02-14T19:31:25Z","pushed_at":"2023-08-29T09:44:14Z","stargazers_count":99,"language":"Ruby"},{"full_name":"kazuhiro4949/EditDistance","description":"Incremental update tool to UITableView and UICollectionView","topics":["swift","uitableview","uicollectionview","editdistance","ios","carthage","algorithm","cocoapods"],"created_at":"2017-02-18T11:43:17Z","pushed_at":"2019-06-15T03:58:43Z","stargazers_count":90,"language":"Swift"},{"full_name":"WorldDownTown/Benchmark","description":"The Benchmark⏲ module provides methods to measure and report the time used to execute Swift code.","topics":["swift","benchmark","carthage","cocoapods"],"created_at":"2016-05-24T14:43:37Z","pushed_at":"2017-05-05T01:41:04Z","stargazers_count":86,"language":"Objective-C"},{"full_name":"efremidze/NumPad","description":"Number Pad (inspired by Square)","topics":["numpad","keyboard","digits","swift","square","cocoapods","number","pad","apple","carthage"],"created_at":"2016-01-06T21:04:56Z","pushed_at":"2019-03-26T23:08:02Z","stargazers_count":84,"language":"Swift"},{"full_name":"yysskk/MemoryCache","description":"LRU, type-safe, thread-safe memory cache class in Swift","topics":["ios","memory-cache","swift","utility","cocoapods","carthage","expiration","lru-cache"],"created_at":"2019-01-23T07:37:28Z","pushed_at":"2021-04-29T20:25:37Z","stargazers_count":78,"language":"Swift"},{"full_name":"SwiftKitz/Notificationz","description":"📡 Helping you own NotificationCenter in Swift!","topics":["notification-center","swift","ios","macos","watchos","raii","cocoapods","carthage"],"created_at":"2015-11-18T03:11:16Z","pushed_at":"2019-06-24T19:24:50Z","stargazers_count":77,"language":"Swift"},{"full_name":"floriankrueger/Manuscript","description":"AutoLayoutKit in pure Swift.","topics":["swift","carthage","autolayout","tvos","ios","cocoapods","manuscript","uikit"],"created_at":"2015-04-24T06:14:20Z","pushed_at":"2017-04-19T12:53:29Z","stargazers_count":76,"language":"Swift"},{"full_name":"bugfender/BugfenderSDK-iOS","description":"Bugfender SDK for iOS, a remote logger tailor-made for mobile","topics":["objective-c","bugfender","sdk","ios","ios-swift","cocoapods","logging"],"created_at":"2014-10-16T13:26:46Z","pushed_at":"2024-09-04T10:54:26Z","stargazers_count":76,"language":"Objective-C"},{"full_name":"semver4j/semver4j","description":"Semantic versioning for Java apps.","topics":["java","node-semver","semver","cocoapods","ivy","semver4j","semantic-versioning"],"created_at":"2022-07-12T15:26:11Z","pushed_at":"2024-11-05T06:32:17Z","stargazers_count":74,"language":"Java"},{"full_name":"nvzqz/Threadly","description":"Type-safe thread-local storage in Swift","topics":["thread","swift","cocoapods","carthage","type-safety","concurrency","macos","ios","tvos","linux"],"created_at":"2017-06-21T22:46:59Z","pushed_at":"2018-11-06T21:01:52Z","stargazers_count":74,"language":"Swift"},{"full_name":"cagricolak/CoreCharts","description":"Core Charts | Basic Scrollable Chart Library for iOS","topics":["chart","barchart","charts","swift-library","corecharts","ios","cocoapods"],"created_at":"2018-04-22T20:32:19Z","pushed_at":"2019-12-02T07:33:55Z","stargazers_count":71,"language":"Ruby"},{"full_name":"WorldDownTown/CSS3ColorsSwift","description":"A UIColor extension with CSS3 Color names.","topics":["uicolor","swift","cocoapods","carthage","snippets"],"created_at":"2016-11-06T16:42:33Z","pushed_at":"2016-11-13T15:09:01Z","stargazers_count":67,"language":"Ruby"},{"full_name":"awesome-labs/LFTimePicker","description":"Custom Time Picker ViewController with Selection of start and end times in Swift :large_orange_diamond:","topics":["swift","time-picker","ios","awesome","dribbble","cocoapods"],"created_at":"2016-06-02T08:47:47Z","pushed_at":"2017-07-31T02:56:00Z","stargazers_count":67,"language":"Swift"},{"full_name":"aimalygin/StableCollectionViewLayout","description":"UICollectionViewLayout adjusts a content offset if the collection view is updated","topics":["cocoapods","ios","swift","carthage","contentoffset","spm","uicollectionview","uicollectionviewlayout","uikit"],"created_at":"2021-04-07T11:59:22Z","pushed_at":"2023-11-29T06:06:52Z","stargazers_count":66,"language":"Swift"},{"full_name":"nferocious76/AutoCompleteTextField","description":"TextField with smart suggestion for email inputs","topics":["carthage","cocoapods","ios","ios-development","swift","email-suggestion","smart-suggestion"],"created_at":"2016-03-18T18:34:26Z","pushed_at":"2023-09-05T02:04:41Z","stargazers_count":65,"language":"Ruby"},{"full_name":"Boilertalk/BlockiesSwift","description":"Unique blocky identicons generator for Swift","topics":["ethereum","blockies","identicon","identicon-generator","identicon-avatar","cocoapods","carthage","swift","cocoa","ios"],"created_at":"2017-12-20T02:10:25Z","pushed_at":"2023-03-01T10:07:45Z","stargazers_count":64,"language":"Swift"},{"full_name":"serejahh/UnboxedAlamofire","description":"[Deprecated] Alamofire + Unbox: the easiest way to download and decode JSON into swift objects.","topics":["alamofire","unbox","swift","json","cocoapods","carthage","ios","macos"],"created_at":"2016-07-31T19:05:53Z","pushed_at":"2021-03-18T06:51:32Z","stargazers_count":64,"language":"Ruby"},{"full_name":"AlTavares/Ciao","description":"Publish and discover services using Bonjour","topics":["carthage","cocoapods","xcode","swift","mdns","zeroconf","bonjour"],"created_at":"2017-10-10T14:20:52Z","pushed_at":"2024-07-15T20:59:21Z","stargazers_count":63,"language":"Swift"},{"full_name":"abdullahselek/SwiftyMessenger","description":"Swift toolkit for passing messages between iOS apps and extensions.","topics":["inter-process-communication","listen-messages","cocoapods","watchconnectivity-framework","carthage","xcode","app-extension","ios","ios-extension"],"created_at":"2018-05-15T14:25:35Z","pushed_at":"2021-02-09T19:39:16Z","stargazers_count":61,"language":"Objective-C"},{"full_name":"bonyadmitr/KeyboardHideManager","description":"Codeless manager to hide keyboard by tapping on views for iOS written in Swift","topics":["cocoapods","codeless","swift","keyboard","ios","touch","swift-3","swift3","framework","library"],"created_at":"2016-12-05T21:44:35Z","pushed_at":"2024-05-30T12:34:56Z","stargazers_count":57,"language":"Swift"},{"full_name":"JARMourato/EasyAbout","description":"A way to easily add Cocoapod licenses and App Version to your iOS App using the Settings Bundle","topics":["cocoapods","about","acknowledgements"],"created_at":"2016-02-13T01:39:29Z","pushed_at":"2019-05-23T17:45:05Z","stargazers_count":55,"language":"Ruby"},{"full_name":"keitaoouchi/OcticonsKit","description":"Use Octicons in your Swift projects.","topics":["carthage","cocoapods","ios-ui","ios-swift","uifont","uiimage","swift","octicons"],"created_at":"2016-09-17T16:47:41Z","pushed_at":"2018-06-09T05:23:35Z","stargazers_count":54,"language":"Swift"},{"full_name":"abdullahselek/Lighty","description":"Easy to use and lightweight logger for iOS, macOS, tvOS, watchOS and Linux in Swift.","topics":["logger","logging-library","cocoapods","carthage","swift"],"created_at":"2016-12-17T17:48:22Z","pushed_at":"2024-05-14T10:41:01Z","stargazers_count":52,"language":"Objective-C"},{"full_name":"T-Pham/NoOptionalInterpolation","description":"✍️ No \"Optional(...)\" in string interpolation + Easy pluralization","topics":["swift","optional","pluralization","plural-form","cocoapods","podfile","cartfile","carthage","ios","osx"],"created_at":"2016-05-27T09:14:18Z","pushed_at":"2017-10-24T09:02:25Z","stargazers_count":51,"language":"Ruby"},{"full_name":"iAmrSalman/StorageManager","description":"Safe and easy way to use FileManager as Database","topics":["iamrsalman","filemanager","swift","ios","macos","tvos","watchos","cocoapods","carthage","xcode"],"created_at":"2017-09-23T21:18:42Z","pushed_at":"2019-08-26T08:24:15Z","stargazers_count":50,"language":"Ruby"},{"full_name":"efekanegeli/EEStackLayout","description":"A structured vertical/horizontal stack layout","topics":["swift","stacklayout","tags","cocoapods","stack"],"created_at":"2018-06-06T11:43:37Z","pushed_at":"2019-11-26T18:29:41Z","stargazers_count":50,"language":"Swift"},{"full_name":"ppth0608/BPCircleActivityIndicator","description":" A lightweight and awesome loading Activity Indicator for your iOS app.","topics":["ios","swift","swift3","activityindicator","loadingview","loading-spinner","ui","cocoapods","animation","storyboard-setup"],"created_at":"2017-04-16T04:42:54Z","pushed_at":"2017-04-24T15:02:22Z","stargazers_count":46,"language":"Ruby"},{"full_name":"ethenyl/JamfKit","description":"A Jamf Classic communication framework written in Swift","topics":["swift","jamf","jss","carthage","cocoapods","jamf-pro","ios","macos","apple","framework"],"created_at":"2017-10-25T12:38:31Z","pushed_at":"2019-06-10T19:05:56Z","stargazers_count":41,"language":"Ruby"},{"full_name":"iAmrSalman/Dots","description":"Lightweight Concurrent Networking Framework","topics":["iamrsalman","swift","networking","concurrency","ios","macos","tvos","watchos","cocoapods","carthage"],"created_at":"2017-04-04T00:42:57Z","pushed_at":"2018-04-08T23:34:20Z","stargazers_count":38,"language":"Ruby"},{"full_name":"michaelhenry/deploy-to-cocoapods-github-action","description":"Github action for deploying to Cocoapods.org","topics":["github-actions","github","ci","automation","cocoapods","pod"],"created_at":"2019-09-22T04:56:58Z","pushed_at":"2022-01-16T13:26:24Z","stargazers_count":37,"language":"JavaScript"},{"full_name":"amantaneja/PTEventView","description":"An Event View based on Apple's Event Detail View. Written in Swift 3. Supports ARC, Autolayout and editing via StoryBoard.","topics":["calendar","cocoapods","swift","apple-event","ibdesignable","cocoapod","cocoa-touch","autolayout","storyboard","pteventview"],"created_at":"2017-08-20T10:42:39Z","pushed_at":"2020-05-07T06:57:14Z","stargazers_count":35,"language":"Ruby"},{"full_name":"nbolatov/Intro","description":"An iOS framework to easily create simple animated walkthrough, written in Swift.","topics":["cocoapods","swift","intro","walkthrough","tutorial","ios","cocoapod","animation"],"created_at":"2016-12-22T09:30:01Z","pushed_at":"2017-01-13T05:53:07Z","stargazers_count":33,"language":"Swift"},{"full_name":"VirgilSecurity/virgil-sdk-x","description":"Virgil Core SDK allows developers to get up and running with Virgil Cards Service API quickly and add end-to-end security to their new or existing digital solutions to become HIPAA and GDPR compliant and more.","topics":["carthage","cocoapods","swift","cryptography","pki","sdk","end-to-end-encryption","encryption","gdpr","hipaa"],"created_at":"2015-09-01T03:18:50Z","pushed_at":"2023-08-14T03:13:39Z","stargazers_count":27,"language":"Objective-C"},{"full_name":"iceman201/TaniwhaTextField","description":"My first cocoapod framework","topics":["ios","swift","swift3","textfield","swift-framework","swift-package-manager","framework","animation","ios-sdk","cocoapods"],"created_at":"2017-06-22T14:31:44Z","pushed_at":"2023-12-09T08:30:04Z","stargazers_count":26,"language":"Ruby"},{"full_name":"T-Pro/CircularRevealKit","description":"Circular reveal animations made easy","topics":["material-design","uinavigationcontroller","cocoapods","swift5"],"created_at":"2017-04-14T12:18:07Z","pushed_at":"2020-07-11T22:12:22Z","stargazers_count":25,"language":"Ruby"},{"full_name":"fulldecent/FDTextFieldTableViewCell","description":"A UITableViewCell with an editable text field","topics":["swift","cocoapods","uitableviewcell","ui","ui-components"],"created_at":"2016-06-13T15:11:19Z","pushed_at":"2019-12-02T19:04:15Z","stargazers_count":25,"language":"Swift"},{"full_name":"abdullahselek/ContactsWrapper","description":"Contacts wrapper for iOS 9 or upper with Objective-C","topics":["contacts-wrapper","contacts","xcode","cocoapods","carthage"],"created_at":"2016-08-01T17:21:47Z","pushed_at":"2024-05-14T10:37:28Z","stargazers_count":22,"language":"Objective-C"},{"full_name":"AlekseyPleshkov/UIMenuScroll","description":"The horizontal swiping navigation like on Facebook Messenger.","topics":["uimenuscroll","pods","cocoapods","cocoapods-plugin","menu","navigation"],"created_at":"2018-10-13T08:26:57Z","pushed_at":"2018-11-24T16:00:43Z","stargazers_count":19,"language":"Swift"},{"full_name":"dimpiax/StyleDecorator","description":"Easy string decoration with styles","topics":["swift-3","library","decorator","attributedstring","style","ios","cocoapods"],"created_at":"2016-12-25T00:47:42Z","pushed_at":"2019-11-10T17:36:29Z","stargazers_count":15,"language":"Ruby"},{"full_name":"denissimon/prediction-builder-swift","description":"A library for machine learning that builds predictions using a linear regression.","topics":["prediction","regression","machine-learning","swift-library","swift","cocoapods","carthage","swift-package-manager","ml","xcode"],"created_at":"2017-01-15T01:44:23Z","pushed_at":"2024-01-20T20:44:04Z","stargazers_count":12,"language":"Swift"},{"full_name":"bernikovich/NSTEasyJSON","description":"The better way to deal with JSON in Objective-C (inspired by SwiftyJSON)","topics":["ios","objective-c","json","swiftyjson","cocoapods"],"created_at":"2016-12-16T08:30:30Z","pushed_at":"2018-06-18T13:14:21Z","stargazers_count":12,"language":"Objective-C"},{"full_name":"jogendra/JSButton","description":"A fully customisable swift subclass on UIButton which allows you to create beautiful buttons without writing any line of code.","topics":["swift","swift-3","swift-language","ios","ios-app","ios-ui","apple","identity-inspector","storyboard","cocoapods"],"created_at":"2017-07-31T18:33:39Z","pushed_at":"2018-04-06T21:27:47Z","stargazers_count":12,"language":"Swift"},{"full_name":"VirgilSecurity/virgil-sdk-pfs-x","description":"Virgil PFS SDK Objective-C/Swift","topics":["virgil-pfs-sdk","carthage","cocoapods","swift","encryption","virgil-cards","cryptography","pki","perfect-forward-secrecy"],"created_at":"2017-06-12T12:34:40Z","pushed_at":"2019-03-21T11:58:16Z","stargazers_count":3,"language":"Swift"},{"full_name":"andreadelfante/DataFixture","description":"Creation of data model easily, with no headache.","topics":["cocoapods","fixture","realm","pods","library","swift","ios","realmswift","seeders","fake"],"created_at":"2020-01-27T12:51:30Z","pushed_at":"2022-10-06T09:08:54Z","stargazers_count":3,"language":"Swift"}],"frecuent_topics":{"cocoapods":257,"swift":202,"ios":168,"carthage":143,"xcode":34}}