{"category_type":"topic","category_name":"codecov-badge","repos_data":[{"full_name":"NullPointerDepressiveDisorder/MiddleDrag","description":" Three-finger trackpad gestures for middle-click and middle-drag on macOS","topics":["macos","menu-bar-app","middle-click","swift","trackpad","learn","free","open-source","codecov-badge","fossa-status"],"created_at":"2025-11-25T22:54:51Z","pushed_at":"2026-01-19T08:37:57Z","stargazers_count":47,"language":"Swift"}],"frecuent_topics":{"macos":1,"menu-bar-app":1,"middle-click":1,"swift":1,"trackpad":1}}