{"category_type":"topic","category_name":"configuration-files","repos_data":[{"full_name":"HBNetwork/python-decouple","description":"Strict separation of config from code.","topics":["python","configuration-files","environment-variables"],"created_at":"2014-02-25T04:16:08Z","pushed_at":"2024-01-20T20:30:56Z","stargazers_count":2761,"language":"Python"},{"full_name":"marzer/tomlplusplus","description":"Header-only TOML config file parser and serializer for C++17.","topics":["toml","cplusplus-17","cplusplus-20","header-only","configuration-files","cpp","cpp17","cpp20","parser","serializer"],"created_at":"2019-11-27T19:34:20Z","pushed_at":"2024-07-12T09:04:25Z","stargazers_count":1505,"language":"C++"},{"full_name":"cristalhq/aconfig","description":"Simple, useful and opinionated config loader.","topics":["go","golang","dependency-free","config","configuration","configuration-files","environment-variables","command-line","json","yaml"],"created_at":"2020-06-26T19:43:20Z","pushed_at":"2024-03-08T10:29:05Z","stargazers_count":535,"language":"Go"},{"full_name":"martinh/libconfuse","description":"Small configuration file parser library for C.","topics":["config","configuration-files"],"created_at":"2014-01-10T06:34:13Z","pushed_at":"2024-02-17T18:52:42Z","stargazers_count":468,"language":"Shell"},{"full_name":"Boeing/config-file-validator","description":"Cross Platform tool to validate configuration files","topics":["configuration-files","go","golang","developer-tools","devops","config","files","json","xml","yaml"],"created_at":"2022-12-06T01:23:11Z","pushed_at":"2024-08-15T22:28:10Z","stargazers_count":311,"language":"Dockerfile"}],"frecuent_topics":{"configuration-files":5,"config":3,"environment-variables":2,"go":2,"golang":2}}