{"category_type":"topic","category_name":"corelocation","repos_data":[{"full_name":"ProjectDent/ARKit-CoreLocation","description":"Combines the high accuracy of AR with the scale of GPS data.","topics":["corelocation","gps-data","north-calibration","arkit","augmented-reality"],"created_at":"2017-07-15T18:29:21Z","pushed_at":"2024-04-19T09:12:26Z","stargazers_count":5481,"language":"Ruby"},{"full_name":"fulldecent/corelocationcli","description":"Command line program to print location information from CoreLocation","topics":["corelocation","application","swift","gps","location","location-services","gps-tracker","gps-tracking","gps-location"],"created_at":"2014-08-27T00:40:41Z","pushed_at":"2024-11-15T21:00:34Z","stargazers_count":218,"language":"Swift"},{"full_name":"benzamin/BBLocationManager","description":"A Location Manager for easily implementing location services & geofencing in iOS. Ready for iOS 11.","topics":["cocoapods","geocoder","location","corelocation","geofence","geofences","locationmanager","block","delegate","ios"],"created_at":"2017-01-29T10:03:12Z","pushed_at":"2018-01-18T11:14:55Z","stargazers_count":106,"language":"Objective-C"}],"frecuent_topics":{"corelocation":3,"location":2,"gps-data":1,"north-calibration":1,"arkit":1}}