{"category_type":"topic","category_name":"crates","repos_data":[{"full_name":"avinashshenoy97/RusticSOM","description":"Rust library for Self Organising Maps (SOM).","topics":["machine-learning","som","self-organizing-map","ml","rust","rust-library","crates"],"created_at":"2018-03-04T07:44:42Z","pushed_at":"2022-10-15T10:49:14Z","stargazers_count":36,"language":"Rust"},{"full_name":"wowinter13/solscan-mcp","description":"An MCP server for querying Solana transactions using natural language with Solscan API","topics":["crate","crates","mcp","mcp-client","mcp-server","modelcontextprotocol","rust","solana","solana-sdk","solscan"],"created_at":"2025-04-10T14:17:43Z","pushed_at":"2025-08-15T20:48:43Z","stargazers_count":35,"language":"Rust"}],"frecuent_topics":{"rust":2,"crates":2,"machine-learning":1,"som":1,"self-organizing-map":1}}