{"category_type":"topic","category_name":"debugger","repos_data":[{"full_name":"x64dbg/x64dbg","description":"An open-source user mode debugger for Windows. Optimized for reverse engineering and malware analysis.","topics":["debugger","windows","x64","disassembler","reverse-engineering","security","x86","x86-64","malware-analysis","security-tools"],"created_at":"2015-04-11T20:48:23Z","pushed_at":"2025-12-14T13:45:50Z","stargazers_count":47362,"language":"C++"},{"full_name":"cyrus-and/gdb-dashboard","description":"Modular visual interface for GDB in Python","topics":["subcommands","gdb-command","dashboard-styles","gdb-commands","divide","stylable-attributes","gdb","python","debugger","visual"],"created_at":"2015-09-09T16:53:23Z","pushed_at":"2025-11-06T16:13:11Z","stargazers_count":12040,"language":"Python"},{"full_name":"jhen0409/react-native-debugger","description":"The standalone app based on official debugger of React Native, and includes React Inspector / Redux DevTools","topics":["react-native","debugger","react-devtools","redux-devtools-extension","electron"],"created_at":"2016-05-29T22:40:01Z","pushed_at":"2023-10-21T02:55:24Z","stargazers_count":10476,"language":"JavaScript"},{"full_name":"horsicq/Detect-It-Easy","description":"Program for determining types of files for Windows, Linux and MacOS.","topics":["debugger","detect","unpacker","disassembler","reverse-engineering","elf","packer","detector","binary-analysis","program-analysis"],"created_at":"2014-06-01T21:37:32Z","pushed_at":"2025-12-15T18:49:00Z","stargazers_count":9849,"language":"JavaScript"},{"full_name":"pry/pry","description":"A runtime developer console and IRB alternative with powerful introspection capabilities.","topics":["irb","console","ruby","debugger","runtime","pry","introspection","reflection"],"created_at":"2010-12-07T08:10:47Z","pushed_at":"2025-12-18T01:51:05Z","stargazers_count":6818,"language":"Ruby"},{"full_name":"golang/vscode-go","description":"Go extension for Visual Studio Code","topics":["vscode","vscode-extension","golang","debugger","visual-studio-code"],"created_at":"2020-03-06T17:52:04Z","pushed_at":"2025-12-18T16:38:56Z","stargazers_count":4165,"language":"TypeScript"},{"full_name":"x64dbg/ScyllaHide","description":"Advanced usermode anti-anti-debugger. Forked from https://bitbucket.org/NtQuery/scyllahide","topics":["anti-debugging","anti-debug","debugging","debugger","debug","x64dbg","ollydbg","hacktoberfest","x64dbg-plugin"],"created_at":"2016-01-27T05:26:30Z","pushed_at":"2024-06-04T22:02:14Z","stargazers_count":3917,"language":"C++"},{"full_name":"deivid-rodriguez/byebug","description":"Debugging in Ruby","topics":["byebug","ruby","debugger","repl"],"created_at":"2013-03-18T20:21:11Z","pushed_at":"2025-12-17T20:01:36Z","stargazers_count":3352,"language":"Ruby"},{"full_name":"inducer/pudb","description":"Full-screen console debugger for Python","topics":["python","debugger","pytest","pytest-plugin","pdb","ipython","bpython","urwid","debug"],"created_at":"2011-05-13T23:44:30Z","pushed_at":"2025-12-15T15:59:14Z","stargazers_count":3183,"language":"Python"},{"full_name":"pkulchenko/ZeroBraneStudio","description":"Lightweight Lua-based IDE for Lua with code completion, syntax highlighting, live coding, remote debugger, and code analyzer; supports Lua 5.1, 5.2, 5.3, 5.4, LuaJIT and other Lua interpreters on Windows, macOS, and Linux","topics":["lua","ide","syntax-highlighting","zerobrane-studio","debugger","editor","lua-engines","zerobrane","wxwidgets-applications"],"created_at":"2011-12-05T00:52:11Z","pushed_at":"2024-05-19T22:43:13Z","stargazers_count":2726,"language":"Lua"},{"full_name":"pmusolino/Wormholy","description":"iOS network debugging, like a wizard 🧙‍♂️","topics":["network","debugger","ios","nsurlsession","alamofire","logger","logging","https","charles"],"created_at":"2018-04-09T14:11:55Z","pushed_at":"2025-10-14T21:18:28Z","stargazers_count":2549,"language":"Swift"},{"full_name":"gotcha/ipdb","description":"Integration of IPython pdb","topics":["python","ipython","debugger"],"created_at":"2011-01-15T17:51:47Z","pushed_at":"2025-07-28T10:12:07Z","stargazers_count":1959,"language":"Python"},{"full_name":"y0ssar1an/q","description":"Quick and dirty debugging output for tired Go programmers","topics":["go","golang","debugger"],"created_at":"2016-02-07T21:57:59Z","pushed_at":"2025-09-04T15:28:36Z","stargazers_count":1552,"language":"Go"},{"full_name":"ionelmc/python-hunter","description":"Hunter is a flexible code tracing toolkit. ","topics":["python","debugging","debugger","tracer"],"created_at":"2015-03-16T18:03:16Z","pushed_at":"2025-08-22T22:15:06Z","stargazers_count":860,"language":"Python"},{"full_name":"unipacker/unipacker","description":"Automatic and platform-independent unpacker for Windows binaries based on emulation","topics":["reverse-engineering","unpacker","pefile","windows","python","security","unicorn-engine","debugger","dumper","emulation"],"created_at":"2019-02-07T16:39:41Z","pushed_at":"2025-08-18T16:24:51Z","stargazers_count":725,"language":"Python"},{"full_name":"Rohansi/Mond","description":"A scripting language for .NET Core","topics":["c-sharp","programming-language","mond","scripting","language","debugger","compiler","scripting-language","dotnet","dotnet-core"],"created_at":"2014-07-13T17:53:10Z","pushed_at":"2025-12-08T20:11:09Z","stargazers_count":387,"language":"C#"},{"full_name":"rocky/zshdb","description":"gdb-like \"trepan\" debugger for zsh","topics":["debugger","zsh","shell"],"created_at":"2008-08-08T17:44:49Z","pushed_at":"2025-10-05T23:45:51Z","stargazers_count":320,"language":"Shell"},{"full_name":"alidavut/locus","description":"Locus is a debugging module for node.js","topics":["nodejs","locus","javascript","debugger"],"created_at":"2013-12-11T13:17:01Z","pushed_at":"2021-09-29T17:56:00Z","stargazers_count":306,"language":"JavaScript"},{"full_name":"ant4g0nist/vegvisir","description":"A browser based GUI for **LLDB** Debugger. ","topics":["reverse-engineering","gui","lldb","python","debugger","macos"],"created_at":"2017-06-17T14:07:23Z","pushed_at":"2021-05-06T19:03:27Z","stargazers_count":199,"language":"Python"},{"full_name":"season-lab/bluepill","description":"BluePill: Neutralizing Anti-Analysis Behavior in Malware Dissection (Black Hat Europe 2019, IEEE TIFS 2020)","topics":["malware-analysis","reverse-engineering","debugger","malware","malware-research"],"created_at":"2019-11-24T21:35:31Z","pushed_at":"2021-12-22T19:03:34Z","stargazers_count":128,"language":"C++"}],"frecuent_topics":{"debugger":20,"python":6,"reverse-engineering":5,"windows":2,"disassembler":2}}