{"category_type":"topic","category_name":"distance-calculation","repos_data":[{"full_name":"orsinium/textdistance","description":"📐 Compute distance between sequences. 30+ algorithms, pure python implementation, common interface, optional external libs usage.","topics":["distance","algorithm","python","textdistance","hamming-distance","levenshtein-distance","damerau-levenshtein","damerau-levenshtein-distance","algorithms","distance-calculation"],"created_at":"2017-05-05T08:46:10Z","pushed_at":"2024-04-24T11:36:15Z","stargazers_count":3302,"language":"Python"},{"full_name":"mjaschen/phpgeo","description":"Simple Yet Powerful Geo Library for PHP","topics":["php","vincenty","polyline","area-calculator","coordinates","geofence","distance-calculation","gps","simplify","douglas-peucker"],"created_at":"2013-02-12T10:35:37Z","pushed_at":"2023-12-07T14:02:54Z","stargazers_count":1536,"language":"PHP"},{"full_name":"ashvardanian/SimSIMD","description":"Up to 200x Faster Inner Products and Vector Similarity — for Python, JavaScript, Rust, and C, supporting f64, f32, f16 real & complex, i8, and binary vectors using SIMD for both x86 AVX2 & AVX-512 and Arm NEON & SVE 📐","topics":["arm-neon","arm-sve","assembly","avx2","distance-calculation","distance-measures","metrics","neon","simd","simd-instructions"],"created_at":"2023-03-14T08:41:48Z","pushed_at":"2024-04-10T19:00:09Z","stargazers_count":717,"language":"CMake"}],"frecuent_topics":{"distance-calculation":3,"distance":1,"algorithm":1,"python":1,"textdistance":1}}