{"category_type":"topic","category_name":"flow","repos_data":[{"full_name":"prettier/prettier","description":"Prettier is an opinionated code formatter.","topics":["formatter","printer","prettier","ast","javascript","flow","typescript","css","scss","less"],"created_at":"2016-11-29T17:13:37Z","pushed_at":"2024-12-02T02:03:56Z","stargazers_count":49523,"language":"JavaScript"},{"full_name":"ReactiveX/RxJava","description":"RxJava – Reactive Extensions for the JVM – a library for composing asynchronous and event-based programs using observable sequences for the Java VM.","topics":["java","rxjava","flow","reactive-streams"],"created_at":"2013-01-08T20:11:48Z","pushed_at":"2024-11-28T09:35:41Z","stargazers_count":47931,"language":"Shell"},{"full_name":"reactor/reactor-core","description":"Non-Blocking Reactive Foundation for the JVM","topics":["reactive","flux","mono","reactive-streams","flow","asynchronous","reactive-extensions","jvm"],"created_at":"2015-11-10T10:06:40Z","pushed_at":"2024-11-28T07:27:01Z","stargazers_count":4996,"language":"Java"},{"full_name":"jerosoler/Drawflow","description":"Simple flow library 🖥️🖱️","topics":["flow","javascript","javascript-library","flow-based-programming","flowchart","visual-programming","dataflow-programming","graph-editor","dataflow","drawflow"],"created_at":"2020-04-21T17:59:14Z","pushed_at":"2024-10-19T21:55:00Z","stargazers_count":4829,"language":"CSS"},{"full_name":"RxSwiftCommunity/RxFlow","description":"RxFlow is a navigation framework for iOS applications based on a Reactive Flow Coordinator pattern","topics":["swift","coordinator","reactive-programming","rxswift","flow"],"created_at":"2017-12-31T02:43:28Z","pushed_at":"2024-01-28T12:33:04Z","stargazers_count":1881,"language":"Ruby"},{"full_name":"sipcapture/homer","description":"HOMER - 100% Open-Source SIP, VoIP, RTC Packet Capture & Monitoring","topics":["monitoring","troubleshooting","voip","rtc","pcap","flow","callflow","cdr","correlation","capture-agent"],"created_at":"2014-03-28T14:11:48Z","pushed_at":"2024-11-11T21:17:47Z","stargazers_count":1661,"language":"Shell"},{"full_name":"LeonardoCardoso/SwiftLinkPreview","description":"It makes a preview from an URL, grabbing all the information such as title, relevant texts and images.","topics":["swift","flow","watchos","tvos","macos","ios","carthage","cocoapods","swift-package-manager","crawler"],"created_at":"2016-06-09T12:32:25Z","pushed_at":"2023-08-31T02:55:44Z","stargazers_count":1374,"language":"Ruby"},{"full_name":"ClementPinard/FlowNetPytorch","description":"Pytorch implementation of FlowNet by Dosovitskiy et al.","topics":["pytorch","flownet","flow"],"created_at":"2017-01-27T14:58:42Z","pushed_at":"2024-03-24T21:21:02Z","stargazers_count":854,"language":"Python"},{"full_name":"andreadelfante/PredicateFlow","description":"Write amazing, strong-typed and easy-to-read NSPredicate.","topics":["cocoapods","flow","autogenerated","code-generation","swift","ios","macos","watchos","tvos","realmswift"],"created_at":"2018-02-26T21:40:31Z","pushed_at":"2023-03-17T05:48:13Z","stargazers_count":101,"language":"Ruby"},{"full_name":"roytornado/Flow-iOS","description":"Make your logic flow and data flow clean and human readable","topics":["swift","flow","design-pattern","chain-of-responsibility","operation","nsoperation","nsoperationqueue","callback-hell"],"created_at":"2016-10-14T08:25:25Z","pushed_at":"2017-08-16T07:53:22Z","stargazers_count":21,"language":"Swift"},{"full_name":"dotflow-io/dotflow","description":"🎲 Dotflow turns an idea into flow!","topics":["data","data-structures","database","dataflow","dataflow-programming","etl","etl-framework","etl-pipeline","flow","python"],"created_at":"2024-12-26T03:05:48Z","pushed_at":"2025-03-07T02:50:04Z","stargazers_count":1,"language":"Python"}],"frecuent_topics":{"flow":11,"swift":4,"javascript":2,"reactive-streams":2,"dataflow-programming":2}}