{"category_type":"topic","category_name":"gone-io","repos_data":[{"full_name":"gone-io/gone","description":"🚀 Gone - A Lightweight Dependency Injection Framework for Go | Tag-based Auto Injection | Supports Config Center/Lifecycle Management | Provides Rich Ecosystem Components and Scaffolding Tool","topics":["di","dependency-injection","dig","golang","wire","gone","gone-io","goner"],"created_at":"2022-10-16T03:27:08Z","pushed_at":"2025-12-15T04:13:48Z","stargazers_count":132,"language":"Go"}],"frecuent_topics":{"di":1,"dependency-injection":1,"dig":1,"golang":1,"wire":1}}