{"category_type":"topic","category_name":"ion","repos_data":[{"full_name":"rsteube/carapace-bin","description":"multi-shell multi-command argument completer","topics":["bash","elvish","fish","powershell","zsh","oil","xonsh","ion","nushell","tcsh"],"created_at":"2020-04-20T20:49:41Z","pushed_at":"2024-12-01T16:21:45Z","stargazers_count":970,"language":"Go"},{"full_name":"rsteube/carapace-spec","description":"define simple completions using a spec file","topics":["bash","completion","elvish","fish","ion","nushell","oil","powershell","tcsh","xonsh"],"created_at":"2022-04-30T23:13:12Z","pushed_at":"2024-11-30T15:01:21Z","stargazers_count":19,"language":"Go"}],"frecuent_topics":{"bash":2,"elvish":2,"fish":2,"powershell":2,"oil":2}}