{"category_type":"topic","category_name":"jruby","repos_data":[{"full_name":"elastic/logstash","description":"Logstash - transport and process your logs, events, or other data","topics":["etl-framework","streaming","logging","java","jruby","real-time-processing"],"created_at":"2010-11-18T01:31:50Z","pushed_at":"2026-01-19T06:14:35Z","stargazers_count":14765,"language":"Ruby"},{"full_name":"rvm/rvm","description":"Ruby enVironment Manager (RVM)","topics":["rvm","ruby","ruby-versions","ruby-environment","jruby","rbx","rubinius","mri-ruby","truffleruby","mruby"],"created_at":"2009-08-24T00:59:44Z","pushed_at":"2026-01-10T22:31:04Z","stargazers_count":5187,"language":"Ruby"},{"full_name":"postmodern/ruby-install","description":"Installs Ruby, JRuby, TruffleRuby, or mruby","topics":["ruby","installer","jruby","truffleruby","mruby","rubies","ruby-install","bash-script","bash-utility","ruby-installer"],"created_at":"2013-02-24T02:50:09Z","pushed_at":"2026-01-14T01:32:41Z","stargazers_count":1963,"language":"Shell"},{"full_name":"shoes/shoes4","description":"Shoes 4 : the next version of Shoes","topics":["shoes","ruby","jruby","gui","swt","mac-osx","linux","windows","cross-platform"],"created_at":"2012-05-24T14:57:59Z","pushed_at":"2023-11-17T21:43:57Z","stargazers_count":1610,"language":"Ruby"},{"full_name":"AndyObtiva/glimmer","description":"DSL Framework consisting of a DSL Engine and a Data-Binding Library used in Glimmer DSL for SWT (JRuby Desktop Development GUI Framework), Glimmer DSL for Opal (Pure Ruby Web GUI), Glimmer DSL for LibUI (Prerequisite-Free Ruby Desktop Development GUI Library), Glimmer DSL for Tk (Ruby Tk Desktop Development GUI Library), Glimmer DSL for GTK (Ruby-GNOME Desktop Development GUI Library), Glimmer DSL for XML (& HTML), and Glimmer DSL for CSS","topics":["desktop","desktop-application-sdk","ruby","jruby","glimmer","gui-framework","gui-toolkit","gui","swt","macos"],"created_at":"2008-12-04T19:24:35Z","pushed_at":"2025-12-03T23:56:21Z","stargazers_count":814,"language":"Ruby"}],"frecuent_topics":{"jruby":5,"ruby":4,"truffleruby":2,"mruby":2,"gui":2}}