{"category_type":"topic","category_name":"live-coding","repos_data":[{"full_name":"samaaron/sonic-pi","description":"Code. Music. Live.","topics":["livecoding","music","education","schools","synthesis","synthesizer","instrument","live-coding","art","audio"],"created_at":"2013-04-29T11:17:54Z","pushed_at":"2024-11-13T22:00:39Z","stargazers_count":10854,"language":"HTML"},{"full_name":"sloria/doitlive","description":"Because sometimes you need to do it live","topics":["command-line","presentations","python","live-coding","cli","click","bash","zsh","ipython","script"],"created_at":"2014-06-16T02:39:29Z","pushed_at":"2024-11-05T21:04:05Z","stargazers_count":3457,"language":"Python"}],"frecuent_topics":{"live-coding":2,"livecoding":1,"music":1,"education":1,"schools":1}}