{"category_type":"topic","category_name":"nuxtjs","repos_data":[{"full_name":"pi0/bootstrap-vue","description":"MOVED to https://github.com/bootstrap-vue-next/bootstrap-vue-next","topics":["bootstrap","vue","nuxt","nuxtjs","wai-aria","bootstrapvue","components","component-library","accessibility","icons"],"created_at":"2016-10-08T15:59:35Z","pushed_at":"2025-11-13T12:52:41Z","stargazers_count":14496,"language":"JavaScript"}],"frecuent_topics":{"bootstrap":1,"vue":1,"nuxt":1,"nuxtjs":1,"wai-aria":1}}