{"category_type":"topic","category_name":"pluralization","repos_data":[{"full_name":"axuno/SmartFormat","description":"A lightweight text templating library written in C# which can be a drop-in replacement for string.Format","topics":["string-format","string-composition","smartformat","netstandard","netframework","formatter","pluralization","localization"],"created_at":"2010-10-10T18:43:26Z","pushed_at":"2025-01-17T08:29:31Z","stargazers_count":1133,"language":"C#"},{"full_name":"Decybel07/L10n-swift","description":"Localization of the application with ability to change language \"on the fly\" and support for plural form in any language.","topics":["l10n","localization","localized","language","language-detection","change-language","pluralization","plurals","plural-form","stringsdict"],"created_at":"2017-05-11T15:35:52Z","pushed_at":"2024-07-13T10:29:12Z","stargazers_count":316,"language":"Swift"},{"full_name":"T-Pham/NoOptionalInterpolation","description":"✍️ No \"Optional(...)\" in string interpolation + Easy pluralization","topics":["swift","optional","pluralization","plural-form","cocoapods","podfile","cartfile","carthage","ios","osx"],"created_at":"2016-05-27T09:14:18Z","pushed_at":"2017-10-24T09:02:25Z","stargazers_count":51,"language":"Ruby"}],"frecuent_topics":{"pluralization":3,"localization":2,"plural-form":2,"string-format":1,"string-composition":1}}