{"category_type":"topic","category_name":"repository-utilities","repos_data":[{"full_name":"raphaelstolt/lean-package-validator-action","description":"A GitHub Action that validates a project/micro-package for its leanness.","topics":["carbon-footprint","gitattributes","repository-utilities","github-action","datensparsamkeit"],"created_at":"2019-09-03T03:47:48Z","pushed_at":"2025-06-30T14:03:22Z","stargazers_count":0,"language":"PHP"}],"frecuent_topics":{"carbon-footprint":1,"gitattributes":1,"repository-utilities":1,"github-action":1,"datensparsamkeit":1}}