{"category_type":"topic","category_name":"resx-resources","repos_data":[{"full_name":"RickStrahl/Westwind.Globalization","description":"Database driven resource localization for .NET applications","topics":["localization","dotnet-core","dotnet","database-provider","resx-resources"],"created_at":"2013-06-05T20:21:21Z","pushed_at":"2023-03-19T01:42:27Z","stargazers_count":545,"language":"C#"}],"frecuent_topics":{"localization":1,"dotnet-core":1,"dotnet":1,"database-provider":1,"resx-resources":1}}