{"category_type":"topic","category_name":"timezone","repos_data":[{"full_name":"malcommac/SwiftDate","description":"🐔 Toolkit to parse, validate, manipulate, compare and display dates, time & timezones in Swift.","topics":["nsdate-category","swiftdate","date","date-formatting","date-time","timezone","nsdate","swift"],"created_at":"2015-05-06T06:46:24Z","pushed_at":"2023-09-19T09:59:48Z","stargazers_count":7638,"language":"Swift"},{"full_name":"golang-module/carbon","description":"A simple, semantic and developer-friendly golang package for time.","topics":["carbon","date","datetime","time","timezone","lunar","i18n","jalaali","julian","persian"],"created_at":"2020-09-07T09:07:35Z","pushed_at":"2024-12-02T02:40:35Z","stargazers_count":4859,"language":"Go"},{"full_name":"HowardHinnant/date","description":"A date and time library based on the C++11/14/17 <chrono> header","topics":["date","datetime","timezone","calendar","time","iana-database","timezone-library"],"created_at":"2015-07-18T02:34:13Z","pushed_at":"2024-11-22T16:03:13Z","stargazers_count":3173,"language":"C++"},{"full_name":"davedelong/time","description":"Robust and type-safe date and time calculations for Swift","topics":["swift","swift-library","date","datetime","date-time","date-formatting","dates","time","timezone","calendar"],"created_at":"2017-10-31T03:51:23Z","pushed_at":"2024-10-26T22:43:52Z","stargazers_count":2329,"language":"Swift"},{"full_name":"MenoData/Time4J","description":"Advanced date, time and interval library for Java with sun/moon-astronomy and calendars like Chinese, Coptic, Ethiopian, French Republican, Hebrew, Hijri, Historic Christian, Indian National, Japanese, Julian, Korean, Minguo, Persian, Thai, Vietnamese","topics":["java","time4j","calendar","interval","duration","sun","moon","timezone"],"created_at":"2013-07-25T04:50:05Z","pushed_at":"2024-02-11T11:15:08Z","stargazers_count":442,"language":"Java"},{"full_name":"Kawoou/AnyDate","description":"Swifty Date & Time API inspired from Java 8 DateTime API.","topics":["swift","datetime","timezone","java","macos","watchos","tvos","ios","linux"],"created_at":"2017-07-16T22:26:55Z","pushed_at":"2019-04-04T04:26:01Z","stargazers_count":190,"language":"Swift"},{"full_name":"gligorkot/TimeZonePicker","description":"A TimeZonePicker UIViewController similar to the iOS Settings app. Search and select from a range of cities and countries to find your most suitable time zone.","topics":["swift","swift3","swift-3","timezone","timezones","timezone-picker","timezone-library","timezone-list"],"created_at":"2017-07-18T20:33:39Z","pushed_at":"2020-08-05T22:04:31Z","stargazers_count":125,"language":"Swift"},{"full_name":"onmyway133/ISO8601","description":"🎗 Super lightweight ISO8601 Date Formatter in Swift","topics":["ios","iso","8601","date","formatter","timezone"],"created_at":"2016-05-06T22:57:15Z","pushed_at":"2020-05-12T21:32:02Z","stargazers_count":20,"language":"Swift"}],"frecuent_topics":{"timezone":8,"date":5,"swift":4,"datetime":4,"time":3}}