{"category_type":"topic","category_name":"vscode-extension","repos_data":[{"full_name":"viatsko/awesome-vscode","description":"🎨 A curated list of delightful VS Code packages and resources.","topics":["visual-studio","vscode","vscode-theme","vscode-extension","awesome","awesome-list","list","visualstudio","visual-studio-code","visual-studio-code-extension"],"created_at":"2016-02-07T23:02:45Z","pushed_at":"2024-06-21T09:46:41Z","stargazers_count":24817,"language":"JavaScript"},{"full_name":"golang/vscode-go","description":"Go extension for Visual Studio Code","topics":["vscode","vscode-extension","golang","debugger","visual-studio-code"],"created_at":"2020-03-06T17:52:04Z","pushed_at":"2024-09-12T20:12:15Z","stargazers_count":3848,"language":"TypeScript"},{"full_name":"foxundermoon/vs-shell-format","description":"the shellscript、Dockerfile、properties ...... format extension","topics":["vscode-extension","vscode-plugin","shell-extension","bash-format","shell-format","dockerfile","properties","hosts","hostsfile","shfmt"],"created_at":"2017-01-05T15:18:14Z","pushed_at":"2024-09-12T22:27:38Z","stargazers_count":445,"language":"TypeScript"},{"full_name":"mathworks/MATLAB-extension-for-vscode","description":"This extension provides support for editing MATLAB® code in Visual Studio® Code and includes features such as syntax highlighting, code analysis, navigation support, and more.","topics":["matlab","matlab-language","vscode","vscode-extension"],"created_at":"2023-04-06T19:55:43Z","pushed_at":"2024-09-09T14:28:41Z","stargazers_count":230,"language":"TypeScript"},{"full_name":"june07/NiM","description":"Streamline Your Node.js Debugging Workflow with Chromium (Chrome, Edge, More) DevTools.","topics":["nim","nodejs","inspector","debugging","devtools","chrome","chrome-extension","chrome-devtools","vscode","vscode-extension"],"created_at":"2016-11-14T05:49:34Z","pushed_at":"2024-10-17T02:37:33Z","stargazers_count":198,"language":"HTML"},{"full_name":"ipatalas/vscode-postfix-ts","description":"Postfix notation for TypeScript/Javascript - extension for VS Code","topics":["vscode-extension","postfix","typescript"],"created_at":"2017-04-02T16:57:20Z","pushed_at":"2024-06-16T09:52:48Z","stargazers_count":158,"language":"TypeScript"},{"full_name":"cssho/vscode-svgviewer","description":"SVG Viewer for Visual Studio Code","topics":["svg-viewer","vscode","vscode-extension","svg"],"created_at":"2016-02-28T03:48:19Z","pushed_at":"2019-10-22T18:59:26Z","stargazers_count":66,"language":"TypeScript"},{"full_name":"gko/wrap","description":"📦 vscode extension to wrap selection with symbols/pattern","topics":["vscode","vscode-extension","symbols","wrap","selection"],"created_at":"2017-11-22T19:02:25Z","pushed_at":"2023-01-06T01:32:00Z","stargazers_count":14,"language":"TypeScript"}],"frecuent_topics":{"vscode-extension":8,"vscode":6,"visual-studio-code":2,"visual-studio":1,"vscode-theme":1}}