{"category_type":"topic","category_name":"webp-images","repos_data":[{"full_name":"dollarshaveclub/ImageButter","description":"Makes dealing with images buttery smooth.","topics":["ios","webp","webp-images","swift","cocoapods"],"created_at":"2015-09-04T19:55:47Z","pushed_at":"2020-06-26T18:10:33Z","stargazers_count":389,"language":"C"},{"full_name":"vincentorback/WebP-images-with-htaccess","description":"Serving WebP images with htaccess","topics":["webp-images","htaccess"],"created_at":"2013-06-28T07:46:19Z","pushed_at":"2021-06-07T09:15:10Z","stargazers_count":206,"language":"HTML"}],"frecuent_topics":{"webp-images":2,"ios":1,"webp":1,"swift":1,"cocoapods":1}}